[{"op": "÷", "a": 100, "b": 2, "ans": 50}, {"op": "÷", "a": 102, "b": 2, "ans": 51}, {"op": "÷", "a": 104, "b": 2, "ans": 52}, {"op": "÷", "a": 106, "b": 2, "ans": 53}, {"op": "÷", "a": 108, "b": 2, "ans": 54}, {"op": "÷", "a": 110, "b": 2, "ans": 55}, {"op": "÷", "a": 112, "b": 2, "ans": 56}, {"op": "÷", "a": 114, "b": 2, "ans": 57}, {"op": "÷", "a": 116, "b": 2, "ans": 58}, {"op": "÷", "a": 118, "b": 2, "ans": 59}, {"op": "÷", "a": 120, "b": 2, "ans": 60}, {"op": "÷", "a": 122, "b": 2, "ans": 61}, {"op": "÷", "a": 124, "b": 2, "ans": 62}, {"op": "÷", "a": 126, "b": 2, "ans": 63}, {"op": "÷", "a": 128, "b": 2, "ans": 64}, {"op": "÷", "a": 130, "b": 2, "ans": 65}, {"op": "÷", "a": 132, "b": 2, "ans": 66}, {"op": "÷", "a": 134, "b": 2, "ans": 67}, {"op": "÷", "a": 136, "b": 2, "ans": 68}, {"op": "÷", "a": 138, "b": 2, "ans": 69}, {"op": "÷", "a": 140, "b": 2, "ans": 70}, {"op": "÷", "a": 142, "b": 2, "ans": 71}, {"op": "÷", "a": 144, "b": 2, "ans": 72}, {"op": "÷", "a": 146, "b": 2, "ans": 73}, {"op": "÷", "a": 148, "b": 2, "ans": 74}, {"op": "÷", "a": 150, "b": 2, "ans": 75}, {"op": "÷", "a": 152, "b": 2, "ans": 76}, {"op": "÷", "a": 154, "b": 2, "ans": 77}, {"op": "÷", "a": 156, "b": 2, "ans": 78}, {"op": "÷", "a": 158, "b": 2, "ans": 79}, {"op": "÷", "a": 160, "b": 2, "ans": 80}, {"op": "÷", "a": 162, "b": 2, "ans": 81}, {"op": "÷", "a": 164, "b": 2, "ans": 82}, {"op": "÷", "a": 166, "b": 2, "ans": 83}, {"op": "÷", "a": 168, "b": 2, "ans": 84}, {"op": "÷", "a": 170, "b": 2, "ans": 85}, {"op": "÷", "a": 172, "b": 2, "ans": 86}, {"op": "÷", "a": 174, "b": 2, "ans": 87}, {"op": "÷", "a": 176, "b": 2, "ans": 88}, {"op": "÷", "a": 178, "b": 2, "ans": 89}, {"op": "÷", "a": 180, "b": 2, "ans": 90}, {"op": "÷", "a": 182, "b": 2, "ans": 91}, {"op": "÷", "a": 184, "b": 2, "ans": 92}, {"op": "÷", "a": 186, "b": 2, "ans": 93}, {"op": "÷", "a": 188, "b": 2, "ans": 94}, {"op": "÷", "a": 190, "b": 2, "ans": 95}, {"op": "÷", "a": 192, "b": 2, "ans": 96}, {"op": "÷", "a": 194, "b": 2, "ans": 97}, {"op": "÷", "a": 196, "b": 2, "ans": 98}, {"op": "÷", "a": 198, "b": 2, "ans": 99}, {"op": "÷", "a": 200, "b": 2, "ans": 100}, {"op": "÷", "a": 202, "b": 2, "ans": 101}, {"op": "÷", "a": 204, "b": 2, "ans": 102}, {"op": "÷", "a": 206, "b": 2, "ans": 103}, {"op": "÷", "a": 208, "b": 2, "ans": 104}, {"op": "÷", "a": 210, "b": 2, "ans": 105}, {"op": "÷", "a": 212, "b": 2, "ans": 106}, {"op": "÷", "a": 214, "b": 2, "ans": 107}, {"op": "÷", "a": 216, "b": 2, "ans": 108}, {"op": "÷", "a": 218, "b": 2, "ans": 109}, {"op": "÷", "a": 220, "b": 2, "ans": 110}, {"op": "÷", "a": 222, "b": 2, "ans": 111}, {"op": "÷", "a": 224, "b": 2, "ans": 112}, {"op": "÷", "a": 226, "b": 2, "ans": 113}, {"op": "÷", "a": 228, "b": 2, "ans": 114}, {"op": "÷", "a": 230, "b": 2, "ans": 115}, {"op": "÷", "a": 232, "b": 2, "ans": 116}, {"op": "÷", "a": 234, "b": 2, "ans": 117}, {"op": "÷", "a": 236, "b": 2, "ans": 118}, {"op": "÷", "a": 238, "b": 2, "ans": 119}, {"op": "÷", "a": 240, "b": 2, "ans": 120}, {"op": "÷", "a": 242, "b": 2, "ans": 121}, {"op": "÷", "a": 244, "b": 2, "ans": 122}, {"op": "÷", "a": 246, "b": 2, "ans": 123}, {"op": "÷", "a": 248, "b": 2, "ans": 124}, {"op": "÷", "a": 250, "b": 2, "ans": 125}, {"op": "÷", "a": 252, "b": 2, "ans": 126}, {"op": "÷", "a": 254, "b": 2, "ans": 127}, {"op": "÷", "a": 256, "b": 2, "ans": 128}, {"op": "÷", "a": 258, "b": 2, "ans": 129}, {"op": "÷", "a": 260, "b": 2, "ans": 130}, {"op": "÷", "a": 262, "b": 2, "ans": 131}, {"op": "÷", "a": 264, "b": 2, "ans": 132}, {"op": "÷", "a": 266, "b": 2, "ans": 133}, {"op": "÷", "a": 268, "b": 2, "ans": 134}, {"op": "÷", "a": 270, "b": 2, "ans": 135}, {"op": "÷", "a": 272, "b": 2, "ans": 136}, {"op": "÷", "a": 274, "b": 2, "ans": 137}, {"op": "÷", "a": 276, "b": 2, "ans": 138}, {"op": "÷", "a": 278, "b": 2, "ans": 139}, {"op": "÷", "a": 280, "b": 2, "ans": 140}, {"op": "÷", "a": 282, "b": 2, "ans": 141}, {"op": "÷", "a": 284, "b": 2, "ans": 142}, {"op": "÷", "a": 286, "b": 2, "ans": 143}, {"op": "÷", "a": 288, "b": 2, "ans": 144}, {"op": "÷", "a": 290, "b": 2, "ans": 145}, {"op": "÷", "a": 292, "b": 2, "ans": 146}, {"op": "÷", "a": 294, "b": 2, "ans": 147}, {"op": "÷", "a": 296, "b": 2, "ans": 148}, {"op": "÷", "a": 298, "b": 2, "ans": 149}, {"op": "÷", "a": 300, "b": 2, "ans": 150}, {"op": "÷", "a": 302, "b": 2, "ans": 151}, {"op": "÷", "a": 304, "b": 2, "ans": 152}, {"op": "÷", "a": 306, "b": 2, "ans": 153}, {"op": "÷", "a": 308, "b": 2, "ans": 154}, {"op": "÷", "a": 310, "b": 2, "ans": 155}, {"op": "÷", "a": 312, "b": 2, "ans": 156}, {"op": "÷", "a": 314, "b": 2, "ans": 157}, {"op": "÷", "a": 316, "b": 2, "ans": 158}, {"op": "÷", "a": 318, "b": 2, "ans": 159}, {"op": "÷", "a": 320, "b": 2, "ans": 160}, {"op": "÷", "a": 322, "b": 2, "ans": 161}, {"op": "÷", "a": 324, "b": 2, "ans": 162}, {"op": "÷", "a": 326, "b": 2, "ans": 163}, {"op": "÷", "a": 328, "b": 2, "ans": 164}, {"op": "÷", "a": 330, "b": 2, "ans": 165}, {"op": "÷", "a": 332, "b": 2, "ans": 166}, {"op": "÷", "a": 334, "b": 2, "ans": 167}, {"op": "÷", "a": 336, "b": 2, "ans": 168}, {"op": "÷", "a": 338, "b": 2, "ans": 169}, {"op": "÷", "a": 340, "b": 2, "ans": 170}, {"op": "÷", "a": 342, "b": 2, "ans": 171}, {"op": "÷", "a": 344, "b": 2, "ans": 172}, {"op": "÷", "a": 346, "b": 2, "ans": 173}, {"op": "÷", "a": 348, "b": 2, "ans": 174}, {"op": "÷", "a": 350, "b": 2, "ans": 175}, {"op": "÷", "a": 352, "b": 2, "ans": 176}, {"op": "÷", "a": 354, "b": 2, "ans": 177}, {"op": "÷", "a": 356, "b": 2, "ans": 178}, {"op": "÷", "a": 358, "b": 2, "ans": 179}, {"op": "÷", "a": 360, "b": 2, "ans": 180}, {"op": "÷", "a": 362, "b": 2, "ans": 181}, {"op": "÷", "a": 364, "b": 2, "ans": 182}, {"op": "÷", "a": 366, "b": 2, "ans": 183}, {"op": "÷", "a": 368, "b": 2, "ans": 184}, {"op": "÷", "a": 370, "b": 2, "ans": 185}, {"op": "÷", "a": 372, "b": 2, "ans": 186}, {"op": "÷", "a": 374, "b": 2, "ans": 187}, {"op": "÷", "a": 376, "b": 2, "ans": 188}, {"op": "÷", "a": 378, "b": 2, "ans": 189}, {"op": "÷", "a": 380, "b": 2, "ans": 190}, {"op": "÷", "a": 382, "b": 2, "ans": 191}, {"op": "÷", "a": 384, "b": 2, "ans": 192}, {"op": "÷", "a": 386, "b": 2, "ans": 193}, {"op": "÷", "a": 388, "b": 2, "ans": 194}, {"op": "÷", "a": 390, "b": 2, "ans": 195}, {"op": "÷", "a": 392, "b": 2, "ans": 196}, {"op": "÷", "a": 394, "b": 2, "ans": 197}, {"op": "÷", "a": 396, "b": 2, "ans": 198}, {"op": "÷", "a": 398, "b": 2, "ans": 199}, {"op": "÷", "a": 400, "b": 2, "ans": 200}, {"op": "÷", "a": 402, "b": 2, "ans": 201}, {"op": "÷", "a": 404, "b": 2, "ans": 202}, {"op": "÷", "a": 406, "b": 2, "ans": 203}, {"op": "÷", "a": 408, "b": 2, "ans": 204}, {"op": "÷", "a": 410, "b": 2, "ans": 205}, {"op": "÷", "a": 412, "b": 2, "ans": 206}, {"op": "÷", "a": 414, "b": 2, "ans": 207}, {"op": "÷", "a": 416, "b": 2, "ans": 208}, {"op": "÷", "a": 418, "b": 2, "ans": 209}, {"op": "÷", "a": 420, "b": 2, "ans": 210}, {"op": "÷", "a": 422, "b": 2, "ans": 211}, {"op": "÷", "a": 424, "b": 2, "ans": 212}, {"op": "÷", "a": 426, "b": 2, "ans": 213}, {"op": "÷", "a": 428, "b": 2, "ans": 214}, {"op": "÷", "a": 430, "b": 2, "ans": 215}, {"op": "÷", "a": 432, "b": 2, "ans": 216}, {"op": "÷", "a": 434, "b": 2, "ans": 217}, {"op": "÷", "a": 436, "b": 2, "ans": 218}, {"op": "÷", "a": 438, "b": 2, "ans": 219}, {"op": "÷", "a": 440, "b": 2, "ans": 220}, {"op": "÷", "a": 442, "b": 2, "ans": 221}, {"op": "÷", "a": 444, "b": 2, "ans": 222}, {"op": "÷", "a": 446, "b": 2, "ans": 223}, {"op": "÷", "a": 448, "b": 2, "ans": 224}, {"op": "÷", "a": 450, "b": 2, "ans": 225}, {"op": "÷", "a": 452, "b": 2, "ans": 226}, {"op": "÷", "a": 454, "b": 2, "ans": 227}, {"op": "÷", "a": 456, "b": 2, "ans": 228}, {"op": "÷", "a": 458, "b": 2, "ans": 229}, {"op": "÷", "a": 460, "b": 2, "ans": 230}, {"op": "÷", "a": 462, "b": 2, "ans": 231}, {"op": "÷", "a": 464, "b": 2, "ans": 232}, {"op": "÷", "a": 466, "b": 2, "ans": 233}, {"op": "÷", "a": 468, "b": 2, "ans": 234}, {"op": "÷", "a": 470, "b": 2, "ans": 235}, {"op": "÷", "a": 472, "b": 2, "ans": 236}, {"op": "÷", "a": 474, "b": 2, "ans": 237}, {"op": "÷", "a": 476, "b": 2, "ans": 238}, {"op": "÷", "a": 478, "b": 2, "ans": 239}, {"op": "÷", "a": 480, "b": 2, "ans": 240}, {"op": "÷", "a": 482, "b": 2, "ans": 241}, {"op": "÷", "a": 484, "b": 2, "ans": 242}, {"op": "÷", "a": 486, "b": 2, "ans": 243}, {"op": "÷", "a": 488, "b": 2, "ans": 244}, {"op": "÷", "a": 490, "b": 2, "ans": 245}, {"op": "÷", "a": 492, "b": 2, "ans": 246}, {"op": "÷", "a": 494, "b": 2, "ans": 247}, {"op": "÷", "a": 496, "b": 2, "ans": 248}, {"op": "÷", "a": 498, "b": 2, "ans": 249}, {"op": "÷", "a": 500, "b": 2, "ans": 250}, {"op": "÷", "a": 502, "b": 2, "ans": 251}, {"op": "÷", "a": 504, "b": 2, "ans": 252}, {"op": "÷", "a": 506, "b": 2, "ans": 253}, {"op": "÷", "a": 508, "b": 2, "ans": 254}, {"op": "÷", "a": 510, "b": 2, "ans": 255}, {"op": "÷", "a": 512, "b": 2, "ans": 256}, {"op": "÷", "a": 514, "b": 2, "ans": 257}, {"op": "÷", "a": 516, "b": 2, "ans": 258}, {"op": "÷", "a": 518, "b": 2, "ans": 259}, {"op": "÷", "a": 520, "b": 2, "ans": 260}, {"op": "÷", "a": 522, "b": 2, "ans": 261}, {"op": "÷", "a": 524, "b": 2, "ans": 262}, {"op": "÷", "a": 526, "b": 2, "ans": 263}, {"op": "÷", "a": 528, "b": 2, "ans": 264}, {"op": "÷", "a": 530, "b": 2, "ans": 265}, {"op": "÷", "a": 532, "b": 2, "ans": 266}, {"op": "÷", "a": 534, "b": 2, "ans": 267}, {"op": "÷", "a": 536, "b": 2, "ans": 268}, {"op": "÷", "a": 538, "b": 2, "ans": 269}, {"op": "÷", "a": 540, "b": 2, "ans": 270}, {"op": "÷", "a": 542, "b": 2, "ans": 271}, {"op": "÷", "a": 544, "b": 2, "ans": 272}, {"op": "÷", "a": 546, "b": 2, "ans": 273}, {"op": "÷", "a": 548, "b": 2, "ans": 274}, {"op": "÷", "a": 550, "b": 2, "ans": 275}, {"op": "÷", "a": 552, "b": 2, "ans": 276}, {"op": "÷", "a": 554, "b": 2, "ans": 277}, {"op": "÷", "a": 556, "b": 2, "ans": 278}, {"op": "÷", "a": 558, "b": 2, "ans": 279}, {"op": "÷", "a": 560, "b": 2, "ans": 280}, {"op": "÷", "a": 562, "b": 2, "ans": 281}, {"op": "÷", "a": 564, "b": 2, "ans": 282}, {"op": "÷", "a": 566, "b": 2, "ans": 283}, {"op": "÷", "a": 568, "b": 2, "ans": 284}, {"op": "÷", "a": 570, "b": 2, "ans": 285}, {"op": "÷", "a": 572, "b": 2, "ans": 286}, {"op": "÷", "a": 574, "b": 2, "ans": 287}, {"op": "÷", "a": 576, "b": 2, "ans": 288}, {"op": "÷", "a": 578, "b": 2, "ans": 289}, {"op": "÷", "a": 580, "b": 2, "ans": 290}, {"op": "÷", "a": 582, "b": 2, "ans": 291}, {"op": "÷", "a": 584, "b": 2, "ans": 292}, {"op": "÷", "a": 586, "b": 2, "ans": 293}, {"op": "÷", "a": 588, "b": 2, "ans": 294}, {"op": "÷", "a": 590, "b": 2, "ans": 295}, {"op": "÷", "a": 592, "b": 2, "ans": 296}, {"op": "÷", "a": 594, "b": 2, "ans": 297}, {"op": "÷", "a": 596, "b": 2, "ans": 298}, {"op": "÷", "a": 598, "b": 2, "ans": 299}, {"op": "÷", "a": 600, "b": 2, "ans": 300}, {"op": "÷", "a": 602, "b": 2, "ans": 301}, {"op": "÷", "a": 604, "b": 2, "ans": 302}, {"op": "÷", "a": 606, "b": 2, "ans": 303}, {"op": "÷", "a": 608, "b": 2, "ans": 304}, {"op": "÷", "a": 610, "b": 2, "ans": 305}, {"op": "÷", "a": 612, "b": 2, "ans": 306}, {"op": "÷", "a": 614, "b": 2, "ans": 307}, {"op": "÷", "a": 616, "b": 2, "ans": 308}, {"op": "÷", "a": 618, "b": 2, "ans": 309}, {"op": "÷", "a": 620, "b": 2, "ans": 310}, {"op": "÷", "a": 622, "b": 2, "ans": 311}, {"op": "÷", "a": 624, "b": 2, "ans": 312}, {"op": "÷", "a": 626, "b": 2, "ans": 313}, {"op": "÷", "a": 628, "b": 2, "ans": 314}, {"op": "÷", "a": 630, "b": 2, "ans": 315}, {"op": "÷", "a": 632, "b": 2, "ans": 316}, {"op": "÷", "a": 634, "b": 2, "ans": 317}, {"op": "÷", "a": 636, "b": 2, "ans": 318}, {"op": "÷", "a": 638, "b": 2, "ans": 319}, {"op": "÷", "a": 640, "b": 2, "ans": 320}, {"op": "÷", "a": 642, "b": 2, "ans": 321}, {"op": "÷", "a": 644, "b": 2, "ans": 322}, {"op": "÷", "a": 646, "b": 2, "ans": 323}, {"op": "÷", "a": 648, "b": 2, "ans": 324}, {"op": "÷", "a": 650, "b": 2, "ans": 325}, {"op": "÷", "a": 652, "b": 2, "ans": 326}, {"op": "÷", "a": 654, "b": 2, "ans": 327}, {"op": "÷", "a": 656, "b": 2, "ans": 328}, {"op": "÷", "a": 658, "b": 2, "ans": 329}, {"op": "÷", "a": 660, "b": 2, "ans": 330}, {"op": "÷", "a": 662, "b": 2, "ans": 331}, {"op": "÷", "a": 664, "b": 2, "ans": 332}, {"op": "÷", "a": 666, "b": 2, "ans": 333}, {"op": "÷", "a": 668, "b": 2, "ans": 334}, {"op": "÷", "a": 670, "b": 2, "ans": 335}, {"op": "÷", "a": 672, "b": 2, "ans": 336}, {"op": "÷", "a": 674, "b": 2, "ans": 337}, {"op": "÷", "a": 676, "b": 2, "ans": 338}, {"op": "÷", "a": 678, "b": 2, "ans": 339}, {"op": "÷", "a": 680, "b": 2, "ans": 340}, {"op": "÷", "a": 682, "b": 2, "ans": 341}, {"op": "÷", "a": 684, "b": 2, "ans": 342}, {"op": "÷", "a": 686, "b": 2, "ans": 343}, {"op": "÷", "a": 688, "b": 2, "ans": 344}, {"op": "÷", "a": 690, "b": 2, "ans": 345}, {"op": "÷", "a": 692, "b": 2, "ans": 346}, {"op": "÷", "a": 694, "b": 2, "ans": 347}, {"op": "÷", "a": 696, "b": 2, "ans": 348}, {"op": "÷", "a": 698, "b": 2, "ans": 349}, {"op": "÷", "a": 700, "b": 2, "ans": 350}, {"op": "÷", "a": 702, "b": 2, "ans": 351}, {"op": "÷", "a": 704, "b": 2, "ans": 352}, {"op": "÷", "a": 706, "b": 2, "ans": 353}, {"op": "÷", "a": 708, "b": 2, "ans": 354}, {"op": "÷", "a": 710, "b": 2, "ans": 355}, {"op": "÷", "a": 712, "b": 2, "ans": 356}, {"op": "÷", "a": 714, "b": 2, "ans": 357}, {"op": "÷", "a": 716, "b": 2, "ans": 358}, {"op": "÷", "a": 718, "b": 2, "ans": 359}, {"op": "÷", "a": 720, "b": 2, "ans": 360}, {"op": "÷", "a": 722, "b": 2, "ans": 361}, {"op": "÷", "a": 724, "b": 2, "ans": 362}, {"op": "÷", "a": 726, "b": 2, "ans": 363}, {"op": "÷", "a": 728, "b": 2, "ans": 364}, {"op": "÷", "a": 730, "b": 2, "ans": 365}, {"op": "÷", "a": 732, "b": 2, "ans": 366}, {"op": "÷", "a": 734, "b": 2, "ans": 367}, {"op": "÷", "a": 736, "b": 2, "ans": 368}, {"op": "÷", "a": 738, "b": 2, "ans": 369}, {"op": "÷", "a": 740, "b": 2, "ans": 370}, {"op": "÷", "a": 742, "b": 2, "ans": 371}, {"op": "÷", "a": 744, "b": 2, "ans": 372}, {"op": "÷", "a": 746, "b": 2, "ans": 373}, {"op": "÷", "a": 748, "b": 2, "ans": 374}, {"op": "÷", "a": 750, "b": 2, "ans": 375}, {"op": "÷", "a": 752, "b": 2, "ans": 376}, {"op": "÷", "a": 754, "b": 2, "ans": 377}, {"op": "÷", "a": 756, "b": 2, "ans": 378}, {"op": "÷", "a": 758, "b": 2, "ans": 379}, {"op": "÷", "a": 760, "b": 2, "ans": 380}, {"op": "÷", "a": 762, "b": 2, "ans": 381}, {"op": "÷", "a": 764, "b": 2, "ans": 382}, {"op": "÷", "a": 766, "b": 2, "ans": 383}, {"op": "÷", "a": 768, "b": 2, "ans": 384}, {"op": "÷", "a": 770, "b": 2, "ans": 385}, {"op": "÷", "a": 772, "b": 2, "ans": 386}, {"op": "÷", "a": 774, "b": 2, "ans": 387}, {"op": "÷", "a": 776, "b": 2, "ans": 388}, {"op": "÷", "a": 778, "b": 2, "ans": 389}, {"op": "÷", "a": 780, "b": 2, "ans": 390}, {"op": "÷", "a": 782, "b": 2, "ans": 391}, {"op": "÷", "a": 784, "b": 2, "ans": 392}, {"op": "÷", "a": 786, "b": 2, "ans": 393}, {"op": "÷", "a": 788, "b": 2, "ans": 394}, {"op": "÷", "a": 790, "b": 2, "ans": 395}, {"op": "÷", "a": 792, "b": 2, "ans": 396}, {"op": "÷", "a": 794, "b": 2, "ans": 397}, {"op": "÷", "a": 796, "b": 2, "ans": 398}, {"op": "÷", "a": 798, "b": 2, "ans": 399}, {"op": "÷", "a": 800, "b": 2, "ans": 400}, {"op": "÷", "a": 802, "b": 2, "ans": 401}, {"op": "÷", "a": 804, "b": 2, "ans": 402}, {"op": "÷", "a": 806, "b": 2, "ans": 403}, {"op": "÷", "a": 808, "b": 2, "ans": 404}, {"op": "÷", "a": 810, "b": 2, "ans": 405}, {"op": "÷", "a": 812, "b": 2, "ans": 406}, {"op": "÷", "a": 814, "b": 2, "ans": 407}, {"op": "÷", "a": 816, "b": 2, "ans": 408}, {"op": "÷", "a": 818, "b": 2, "ans": 409}, {"op": "÷", "a": 820, "b": 2, "ans": 410}, {"op": "÷", "a": 822, "b": 2, "ans": 411}, {"op": "÷", "a": 824, "b": 2, "ans": 412}, {"op": "÷", "a": 826, "b": 2, "ans": 413}, {"op": "÷", "a": 828, "b": 2, "ans": 414}, {"op": "÷", "a": 830, "b": 2, "ans": 415}, {"op": "÷", "a": 832, "b": 2, "ans": 416}, {"op": "÷", "a": 834, "b": 2, "ans": 417}, {"op": "÷", "a": 836, "b": 2, "ans": 418}, {"op": "÷", "a": 838, "b": 2, "ans": 419}, {"op": "÷", "a": 840, "b": 2, "ans": 420}, {"op": "÷", "a": 842, "b": 2, "ans": 421}, {"op": "÷", "a": 844, "b": 2, "ans": 422}, {"op": "÷", "a": 846, "b": 2, "ans": 423}, {"op": "÷", "a": 848, "b": 2, "ans": 424}, {"op": "÷", "a": 850, "b": 2, "ans": 425}, {"op": "÷", "a": 852, "b": 2, "ans": 426}, {"op": "÷", "a": 854, "b": 2, "ans": 427}, {"op": "÷", "a": 856, "b": 2, "ans": 428}, {"op": "÷", "a": 858, "b": 2, "ans": 429}, {"op": "÷", "a": 860, "b": 2, "ans": 430}, {"op": "÷", "a": 862, "b": 2, "ans": 431}, {"op": "÷", "a": 864, "b": 2, "ans": 432}, {"op": "÷", "a": 866, "b": 2, "ans": 433}, {"op": "÷", "a": 868, "b": 2, "ans": 434}, {"op": "÷", "a": 870, "b": 2, "ans": 435}, {"op": "÷", "a": 872, "b": 2, "ans": 436}, {"op": "÷", "a": 874, "b": 2, "ans": 437}, {"op": "÷", "a": 876, "b": 2, "ans": 438}, {"op": "÷", "a": 878, "b": 2, "ans": 439}, {"op": "÷", "a": 880, "b": 2, "ans": 440}, {"op": "÷", "a": 882, "b": 2, "ans": 441}, {"op": "÷", "a": 884, "b": 2, "ans": 442}, {"op": "÷", "a": 886, "b": 2, "ans": 443}, {"op": "÷", "a": 888, "b": 2, "ans": 444}, {"op": "÷", "a": 890, "b": 2, "ans": 445}, {"op": "÷", "a": 892, "b": 2, "ans": 446}, {"op": "÷", "a": 894, "b": 2, "ans": 447}, {"op": "÷", "a": 896, "b": 2, "ans": 448}, {"op": "÷", "a": 898, "b": 2, "ans": 449}, {"op": "÷", "a": 900, "b": 2, "ans": 450}, {"op": "÷", "a": 902, "b": 2, "ans": 451}, {"op": "÷", "a": 904, "b": 2, "ans": 452}, {"op": "÷", "a": 906, "b": 2, "ans": 453}, {"op": "÷", "a": 908, "b": 2, "ans": 454}, {"op": "÷", "a": 910, "b": 2, "ans": 455}, {"op": "÷", "a": 912, "b": 2, "ans": 456}, {"op": "÷", "a": 914, "b": 2, "ans": 457}, {"op": "÷", "a": 916, "b": 2, "ans": 458}, {"op": "÷", "a": 918, "b": 2, "ans": 459}, {"op": "÷", "a": 920, "b": 2, "ans": 460}, {"op": "÷", "a": 922, "b": 2, "ans": 461}, {"op": "÷", "a": 924, "b": 2, "ans": 462}, {"op": "÷", "a": 926, "b": 2, "ans": 463}, {"op": "÷", "a": 928, "b": 2, "ans": 464}, {"op": "÷", "a": 930, "b": 2, "ans": 465}, {"op": "÷", "a": 932, "b": 2, "ans": 466}, {"op": "÷", "a": 934, "b": 2, "ans": 467}, {"op": "÷", "a": 936, "b": 2, "ans": 468}, {"op": "÷", "a": 938, "b": 2, "ans": 469}, {"op": "÷", "a": 940, "b": 2, "ans": 470}, {"op": "÷", "a": 942, "b": 2, "ans": 471}, {"op": "÷", "a": 944, "b": 2, "ans": 472}, {"op": "÷", "a": 946, "b": 2, "ans": 473}, {"op": "÷", "a": 948, "b": 2, "ans": 474}, {"op": "÷", "a": 950, "b": 2, "ans": 475}, {"op": "÷", "a": 952, "b": 2, "ans": 476}, {"op": "÷", "a": 954, "b": 2, "ans": 477}, {"op": "÷", "a": 956, "b": 2, "ans": 478}, {"op": "÷", "a": 958, "b": 2, "ans": 479}, {"op": "÷", "a": 960, "b": 2, "ans": 480}, {"op": "÷", "a": 962, "b": 2, "ans": 481}, {"op": "÷", "a": 964, "b": 2, "ans": 482}, {"op": "÷", "a": 966, "b": 2, "ans": 483}, {"op": "÷", "a": 968, "b": 2, "ans": 484}, {"op": "÷", "a": 970, "b": 2, "ans": 485}, {"op": "÷", "a": 972, "b": 2, "ans": 486}, {"op": "÷", "a": 974, "b": 2, "ans": 487}, {"op": "÷", "a": 976, "b": 2, "ans": 488}, {"op": "÷", "a": 978, "b": 2, "ans": 489}, {"op": "÷", "a": 980, "b": 2, "ans": 490}, {"op": "÷", "a": 982, "b": 2, "ans": 491}, {"op": "÷", "a": 984, "b": 2, "ans": 492}, {"op": "÷", "a": 986, "b": 2, "ans": 493}, {"op": "÷", "a": 988, "b": 2, "ans": 494}, {"op": "÷", "a": 990, "b": 2, "ans": 495}, {"op": "÷", "a": 992, "b": 2, "ans": 496}, {"op": "÷", "a": 994, "b": 2, "ans": 497}, {"op": "÷", "a": 996, "b": 2, "ans": 498}, {"op": "÷", "a": 998, "b": 2, "ans": 499}, {"op": "÷", "a": 102, "b": 3, "ans": 34}, {"op": "÷", "a": 105, "b": 3, "ans": 35}, {"op": "÷", "a": 108, "b": 3, "ans": 36}, {"op": "÷", "a": 111, "b": 3, "ans": 37}, {"op": "÷", "a": 114, "b": 3, "ans": 38}, {"op": "÷", "a": 117, "b": 3, "ans": 39}, {"op": "÷", "a": 120, "b": 3, "ans": 40}, {"op": "÷", "a": 123, "b": 3, "ans": 41}, {"op": "÷", "a": 126, "b": 3, "ans": 42}, {"op": "÷", "a": 129, "b": 3, "ans": 43}, {"op": "÷", "a": 132, "b": 3, "ans": 44}, {"op": "÷", "a": 135, "b": 3, "ans": 45}, {"op": "÷", "a": 138, "b": 3, "ans": 46}, {"op": "÷", "a": 141, "b": 3, "ans": 47}, {"op": "÷", "a": 144, "b": 3, "ans": 48}, {"op": "÷", "a": 147, "b": 3, "ans": 49}, {"op": "÷", "a": 150, "b": 3, "ans": 50}, {"op": "÷", "a": 153, "b": 3, "ans": 51}, {"op": "÷", "a": 156, "b": 3, "ans": 52}, {"op": "÷", "a": 159, "b": 3, "ans": 53}, {"op": "÷", "a": 162, "b": 3, "ans": 54}, {"op": "÷", "a": 165, "b": 3, "ans": 55}, {"op": "÷", "a": 168, "b": 3, "ans": 56}, {"op": "÷", "a": 171, "b": 3, "ans": 57}, {"op": "÷", "a": 174, "b": 3, "ans": 58}, {"op": "÷", "a": 177, "b": 3, "ans": 59}, {"op": "÷", "a": 180, "b": 3, "ans": 60}, {"op": "÷", "a": 183, "b": 3, "ans": 61}, {"op": "÷", "a": 186, "b": 3, "ans": 62}, {"op": "÷", "a": 189, "b": 3, "ans": 63}, {"op": "÷", "a": 192, "b": 3, "ans": 64}, {"op": "÷", "a": 195, "b": 3, "ans": 65}, {"op": "÷", "a": 198, "b": 3, "ans": 66}, {"op": "÷", "a": 201, "b": 3, "ans": 67}, {"op": "÷", "a": 204, "b": 3, "ans": 68}, {"op": "÷", "a": 207, "b": 3, "ans": 69}, {"op": "÷", "a": 210, "b": 3, "ans": 70}, {"op": "÷", "a": 213, "b": 3, "ans": 71}, {"op": "÷", "a": 216, "b": 3, "ans": 72}, {"op": "÷", "a": 219, "b": 3, "ans": 73}, {"op": "÷", "a": 222, "b": 3, "ans": 74}, {"op": "÷", "a": 225, "b": 3, "ans": 75}, {"op": "÷", "a": 228, "b": 3, "ans": 76}, {"op": "÷", "a": 231, "b": 3, "ans": 77}, {"op": "÷", "a": 234, "b": 3, "ans": 78}, {"op": "÷", "a": 237, "b": 3, "ans": 79}, {"op": "÷", "a": 240, "b": 3, "ans": 80}, {"op": "÷", "a": 243, "b": 3, "ans": 81}, {"op": "÷", "a": 246, "b": 3, "ans": 82}, {"op": "÷", "a": 249, "b": 3, "ans": 83}, {"op": "÷", "a": 252, "b": 3, "ans": 84}, {"op": "÷", "a": 255, "b": 3, "ans": 85}, {"op": "÷", "a": 258, "b": 3, "ans": 86}, {"op": "÷", "a": 261, "b": 3, "ans": 87}, {"op": "÷", "a": 264, "b": 3, "ans": 88}, {"op": "÷", "a": 267, "b": 3, "ans": 89}, {"op": "÷", "a": 270, "b": 3, "ans": 90}, {"op": "÷", "a": 273, "b": 3, "ans": 91}, {"op": "÷", "a": 276, "b": 3, "ans": 92}, {"op": "÷", "a": 279, "b": 3, "ans": 93}, {"op": "÷", "a": 282, "b": 3, "ans": 94}, {"op": "÷", "a": 285, "b": 3, "ans": 95}, {"op": "÷", "a": 288, "b": 3, "ans": 96}, {"op": "÷", "a": 291, "b": 3, "ans": 97}, {"op": "÷", "a": 294, "b": 3, "ans": 98}, {"op": "÷", "a": 297, "b": 3, "ans": 99}, {"op": "÷", "a": 300, "b": 3, "ans": 100}, {"op": "÷", "a": 303, "b": 3, "ans": 101}, {"op": "÷", "a": 306, "b": 3, "ans": 102}, {"op": "÷", "a": 309, "b": 3, "ans": 103}, {"op": "÷", "a": 312, "b": 3, "ans": 104}, {"op": "÷", "a": 315, "b": 3, "ans": 105}, {"op": "÷", "a": 318, "b": 3, "ans": 106}, {"op": "÷", "a": 321, "b": 3, "ans": 107}, {"op": "÷", "a": 324, "b": 3, "ans": 108}, {"op": "÷", "a": 327, "b": 3, "ans": 109}, {"op": "÷", "a": 330, "b": 3, "ans": 110}, {"op": "÷", "a": 333, "b": 3, "ans": 111}, {"op": "÷", "a": 336, "b": 3, "ans": 112}, {"op": "÷", "a": 339, "b": 3, "ans": 113}, {"op": "÷", "a": 342, "b": 3, "ans": 114}, {"op": "÷", "a": 345, "b": 3, "ans": 115}, {"op": "÷", "a": 348, "b": 3, "ans": 116}, {"op": "÷", "a": 351, "b": 3, "ans": 117}, {"op": "÷", "a": 354, "b": 3, "ans": 118}, {"op": "÷", "a": 357, "b": 3, "ans": 119}, {"op": "÷", "a": 360, "b": 3, "ans": 120}, {"op": "÷", "a": 363, "b": 3, "ans": 121}, {"op": "÷", "a": 366, "b": 3, "ans": 122}, {"op": "÷", "a": 369, "b": 3, "ans": 123}, {"op": "÷", "a": 372, "b": 3, "ans": 124}, {"op": "÷", "a": 375, "b": 3, "ans": 125}, {"op": "÷", "a": 378, "b": 3, "ans": 126}, {"op": "÷", "a": 381, "b": 3, "ans": 127}, {"op": "÷", "a": 384, "b": 3, "ans": 128}, {"op": "÷", "a": 387, "b": 3, "ans": 129}, {"op": "÷", "a": 390, "b": 3, "ans": 130}, {"op": "÷", "a": 393, "b": 3, "ans": 131}, {"op": "÷", "a": 396, "b": 3, "ans": 132}, {"op": "÷", "a": 399, "b": 3, "ans": 133}, {"op": "÷", "a": 402, "b": 3, "ans": 134}, {"op": "÷", "a": 405, "b": 3, "ans": 135}, {"op": "÷", "a": 408, "b": 3, "ans": 136}, {"op": "÷", "a": 411, "b": 3, "ans": 137}, {"op": "÷", "a": 414, "b": 3, "ans": 138}, {"op": "÷", "a": 417, "b": 3, "ans": 139}, {"op": "÷", "a": 420, "b": 3, "ans": 140}, {"op": "÷", "a": 423, "b": 3, "ans": 141}, {"op": "÷", "a": 426, "b": 3, "ans": 142}, {"op": "÷", "a": 429, "b": 3, "ans": 143}, {"op": "÷", "a": 432, "b": 3, "ans": 144}, {"op": "÷", "a": 435, "b": 3, "ans": 145}, {"op": "÷", "a": 438, "b": 3, "ans": 146}, {"op": "÷", "a": 441, "b": 3, "ans": 147}, {"op": "÷", "a": 444, "b": 3, "ans": 148}, {"op": "÷", "a": 447, "b": 3, "ans": 149}, {"op": "÷", "a": 450, "b": 3, "ans": 150}, {"op": "÷", "a": 453, "b": 3, "ans": 151}, {"op": "÷", "a": 456, "b": 3, "ans": 152}, {"op": "÷", "a": 459, "b": 3, "ans": 153}, {"op": "÷", "a": 462, "b": 3, "ans": 154}, {"op": "÷", "a": 465, "b": 3, "ans": 155}, {"op": "÷", "a": 468, "b": 3, "ans": 156}, {"op": "÷", "a": 471, "b": 3, "ans": 157}, {"op": "÷", "a": 474, "b": 3, "ans": 158}, {"op": "÷", "a": 477, "b": 3, "ans": 159}, {"op": "÷", "a": 480, "b": 3, "ans": 160}, {"op": "÷", "a": 483, "b": 3, "ans": 161}, {"op": "÷", "a": 486, "b": 3, "ans": 162}, {"op": "÷", "a": 489, "b": 3, "ans": 163}, {"op": "÷", "a": 492, "b": 3, "ans": 164}, {"op": "÷", "a": 495, "b": 3, "ans": 165}, {"op": "÷", "a": 498, "b": 3, "ans": 166}, {"op": "÷", "a": 501, "b": 3, "ans": 167}, {"op": "÷", "a": 504, "b": 3, "ans": 168}, {"op": "÷", "a": 507, "b": 3, "ans": 169}, {"op": "÷", "a": 510, "b": 3, "ans": 170}, {"op": "÷", "a": 513, "b": 3, "ans": 171}, {"op": "÷", "a": 516, "b": 3, "ans": 172}, {"op": "÷", "a": 519, "b": 3, "ans": 173}, {"op": "÷", "a": 522, "b": 3, "ans": 174}, {"op": "÷", "a": 525, "b": 3, "ans": 175}, {"op": "÷", "a": 528, "b": 3, "ans": 176}, {"op": "÷", "a": 531, "b": 3, "ans": 177}, {"op": "÷", "a": 534, "b": 3, "ans": 178}, {"op": "÷", "a": 537, "b": 3, "ans": 179}, {"op": "÷", "a": 540, "b": 3, "ans": 180}, {"op": "÷", "a": 543, "b": 3, "ans": 181}, {"op": "÷", "a": 546, "b": 3, "ans": 182}, {"op": "÷", "a": 549, "b": 3, "ans": 183}, {"op": "÷", "a": 552, "b": 3, "ans": 184}, {"op": "÷", "a": 555, "b": 3, "ans": 185}, {"op": "÷", "a": 558, "b": 3, "ans": 186}, {"op": "÷", "a": 561, "b": 3, "ans": 187}, {"op": "÷", "a": 564, "b": 3, "ans": 188}, {"op": "÷", "a": 567, "b": 3, "ans": 189}, {"op": "÷", "a": 570, "b": 3, "ans": 190}, {"op": "÷", "a": 573, "b": 3, "ans": 191}, {"op": "÷", "a": 576, "b": 3, "ans": 192}, {"op": "÷", "a": 579, "b": 3, "ans": 193}, {"op": "÷", "a": 582, "b": 3, "ans": 194}, {"op": "÷", "a": 585, "b": 3, "ans": 195}, {"op": "÷", "a": 588, "b": 3, "ans": 196}, {"op": "÷", "a": 591, "b": 3, "ans": 197}, {"op": "÷", "a": 594, "b": 3, "ans": 198}, {"op": "÷", "a": 597, "b": 3, "ans": 199}, {"op": "÷", "a": 600, "b": 3, "ans": 200}, {"op": "÷", "a": 603, "b": 3, "ans": 201}, {"op": "÷", "a": 606, "b": 3, "ans": 202}, {"op": "÷", "a": 609, "b": 3, "ans": 203}, {"op": "÷", "a": 612, "b": 3, "ans": 204}, {"op": "÷", "a": 615, "b": 3, "ans": 205}, {"op": "÷", "a": 618, "b": 3, "ans": 206}, {"op": "÷", "a": 621, "b": 3, "ans": 207}, {"op": "÷", "a": 624, "b": 3, "ans": 208}, {"op": "÷", "a": 627, "b": 3, "ans": 209}, {"op": "÷", "a": 630, "b": 3, "ans": 210}, {"op": "÷", "a": 633, "b": 3, "ans": 211}, {"op": "÷", "a": 636, "b": 3, "ans": 212}, {"op": "÷", "a": 639, "b": 3, "ans": 213}, {"op": "÷", "a": 642, "b": 3, "ans": 214}, {"op": "÷", "a": 645, "b": 3, "ans": 215}, {"op": "÷", "a": 648, "b": 3, "ans": 216}, {"op": "÷", "a": 651, "b": 3, "ans": 217}, {"op": "÷", "a": 654, "b": 3, "ans": 218}, {"op": "÷", "a": 657, "b": 3, "ans": 219}, {"op": "÷", "a": 660, "b": 3, "ans": 220}, {"op": "÷", "a": 663, "b": 3, "ans": 221}, {"op": "÷", "a": 666, "b": 3, "ans": 222}, {"op": "÷", "a": 669, "b": 3, "ans": 223}, {"op": "÷", "a": 672, "b": 3, "ans": 224}, {"op": "÷", "a": 675, "b": 3, "ans": 225}, {"op": "÷", "a": 678, "b": 3, "ans": 226}, {"op": "÷", "a": 681, "b": 3, "ans": 227}, {"op": "÷", "a": 684, "b": 3, "ans": 228}, {"op": "÷", "a": 687, "b": 3, "ans": 229}, {"op": "÷", "a": 690, "b": 3, "ans": 230}, {"op": "÷", "a": 693, "b": 3, "ans": 231}, {"op": "÷", "a": 696, "b": 3, "ans": 232}, {"op": "÷", "a": 699, "b": 3, "ans": 233}, {"op": "÷", "a": 702, "b": 3, "ans": 234}, {"op": "÷", "a": 705, "b": 3, "ans": 235}, {"op": "÷", "a": 708, "b": 3, "ans": 236}, {"op": "÷", "a": 711, "b": 3, "ans": 237}, {"op": "÷", "a": 714, "b": 3, "ans": 238}, {"op": "÷", "a": 717, "b": 3, "ans": 239}, {"op": "÷", "a": 720, "b": 3, "ans": 240}, {"op": "÷", "a": 723, "b": 3, "ans": 241}, {"op": "÷", "a": 726, "b": 3, "ans": 242}, {"op": "÷", "a": 729, "b": 3, "ans": 243}, {"op": "÷", "a": 732, "b": 3, "ans": 244}, {"op": "÷", "a": 735, "b": 3, "ans": 245}, {"op": "÷", "a": 738, "b": 3, "ans": 246}, {"op": "÷", "a": 741, "b": 3, "ans": 247}, {"op": "÷", "a": 744, "b": 3, "ans": 248}, {"op": "÷", "a": 747, "b": 3, "ans": 249}, {"op": "÷", "a": 750, "b": 3, "ans": 250}, {"op": "÷", "a": 753, "b": 3, "ans": 251}, {"op": "÷", "a": 756, "b": 3, "ans": 252}, {"op": "÷", "a": 759, "b": 3, "ans": 253}, {"op": "÷", "a": 762, "b": 3, "ans": 254}, {"op": "÷", "a": 765, "b": 3, "ans": 255}, {"op": "÷", "a": 768, "b": 3, "ans": 256}, {"op": "÷", "a": 771, "b": 3, "ans": 257}, {"op": "÷", "a": 774, "b": 3, "ans": 258}, {"op": "÷", "a": 777, "b": 3, "ans": 259}, {"op": "÷", "a": 780, "b": 3, "ans": 260}, {"op": "÷", "a": 783, "b": 3, "ans": 261}, {"op": "÷", "a": 786, "b": 3, "ans": 262}, {"op": "÷", "a": 789, "b": 3, "ans": 263}, {"op": "÷", "a": 792, "b": 3, "ans": 264}, {"op": "÷", "a": 795, "b": 3, "ans": 265}, {"op": "÷", "a": 798, "b": 3, "ans": 266}, {"op": "÷", "a": 801, "b": 3, "ans": 267}, {"op": "÷", "a": 804, "b": 3, "ans": 268}, {"op": "÷", "a": 807, "b": 3, "ans": 269}, {"op": "÷", "a": 810, "b": 3, "ans": 270}, {"op": "÷", "a": 813, "b": 3, "ans": 271}, {"op": "÷", "a": 816, "b": 3, "ans": 272}, {"op": "÷", "a": 819, "b": 3, "ans": 273}, {"op": "÷", "a": 822, "b": 3, "ans": 274}, {"op": "÷", "a": 825, "b": 3, "ans": 275}, {"op": "÷", "a": 828, "b": 3, "ans": 276}, {"op": "÷", "a": 831, "b": 3, "ans": 277}, {"op": "÷", "a": 834, "b": 3, "ans": 278}, {"op": "÷", "a": 837, "b": 3, "ans": 279}, {"op": "÷", "a": 840, "b": 3, "ans": 280}, {"op": "÷", "a": 843, "b": 3, "ans": 281}, {"op": "÷", "a": 846, "b": 3, "ans": 282}, {"op": "÷", "a": 849, "b": 3, "ans": 283}, {"op": "÷", "a": 852, "b": 3, "ans": 284}, {"op": "÷", "a": 855, "b": 3, "ans": 285}, {"op": "÷", "a": 858, "b": 3, "ans": 286}, {"op": "÷", "a": 861, "b": 3, "ans": 287}, {"op": "÷", "a": 864, "b": 3, "ans": 288}, {"op": "÷", "a": 867, "b": 3, "ans": 289}, {"op": "÷", "a": 870, "b": 3, "ans": 290}, {"op": "÷", "a": 873, "b": 3, "ans": 291}, {"op": "÷", "a": 876, "b": 3, "ans": 292}, {"op": "÷", "a": 879, "b": 3, "ans": 293}, {"op": "÷", "a": 882, "b": 3, "ans": 294}, {"op": "÷", "a": 885, "b": 3, "ans": 295}, {"op": "÷", "a": 888, "b": 3, "ans": 296}, {"op": "÷", "a": 891, "b": 3, "ans": 297}, {"op": "÷", "a": 894, "b": 3, "ans": 298}, {"op": "÷", "a": 897, "b": 3, "ans": 299}, {"op": "÷", "a": 900, "b": 3, "ans": 300}, {"op": "÷", "a": 903, "b": 3, "ans": 301}, {"op": "÷", "a": 906, "b": 3, "ans": 302}, {"op": "÷", "a": 909, "b": 3, "ans": 303}, {"op": "÷", "a": 912, "b": 3, "ans": 304}, {"op": "÷", "a": 915, "b": 3, "ans": 305}, {"op": "÷", "a": 918, "b": 3, "ans": 306}, {"op": "÷", "a": 921, "b": 3, "ans": 307}, {"op": "÷", "a": 924, "b": 3, "ans": 308}, {"op": "÷", "a": 927, "b": 3, "ans": 309}, {"op": "÷", "a": 930, "b": 3, "ans": 310}, {"op": "÷", "a": 933, "b": 3, "ans": 311}, {"op": "÷", "a": 936, "b": 3, "ans": 312}, {"op": "÷", "a": 939, "b": 3, "ans": 313}, {"op": "÷", "a": 942, "b": 3, "ans": 314}, {"op": "÷", "a": 945, "b": 3, "ans": 315}, {"op": "÷", "a": 948, "b": 3, "ans": 316}, {"op": "÷", "a": 951, "b": 3, "ans": 317}, {"op": "÷", "a": 954, "b": 3, "ans": 318}, {"op": "÷", "a": 957, "b": 3, "ans": 319}, {"op": "÷", "a": 960, "b": 3, "ans": 320}, {"op": "÷", "a": 963, "b": 3, "ans": 321}, {"op": "÷", "a": 966, "b": 3, "ans": 322}, {"op": "÷", "a": 969, "b": 3, "ans": 323}, {"op": "÷", "a": 972, "b": 3, "ans": 324}, {"op": "÷", "a": 975, "b": 3, "ans": 325}, {"op": "÷", "a": 978, "b": 3, "ans": 326}, {"op": "÷", "a": 981, "b": 3, "ans": 327}, {"op": "÷", "a": 984, "b": 3, "ans": 328}, {"op": "÷", "a": 987, "b": 3, "ans": 329}, {"op": "÷", "a": 990, "b": 3, "ans": 330}, {"op": "÷", "a": 993, "b": 3, "ans": 331}, {"op": "÷", "a": 996, "b": 3, "ans": 332}, {"op": "÷", "a": 999, "b": 3, "ans": 333}, {"op": "÷", "a": 100, "b": 4, "ans": 25}, {"op": "÷", "a": 104, "b": 4, "ans": 26}, {"op": "÷", "a": 108, "b": 4, "ans": 27}, {"op": "÷", "a": 112, "b": 4, "ans": 28}, {"op": "÷", "a": 116, "b": 4, "ans": 29}, {"op": "÷", "a": 120, "b": 4, "ans": 30}, {"op": "÷", "a": 124, "b": 4, "ans": 31}, {"op": "÷", "a": 128, "b": 4, "ans": 32}, {"op": "÷", "a": 132, "b": 4, "ans": 33}, {"op": "÷", "a": 136, "b": 4, "ans": 34}, {"op": "÷", "a": 140, "b": 4, "ans": 35}, {"op": "÷", "a": 144, "b": 4, "ans": 36}, {"op": "÷", "a": 148, "b": 4, "ans": 37}, {"op": "÷", "a": 152, "b": 4, "ans": 38}, {"op": "÷", "a": 156, "b": 4, "ans": 39}, {"op": "÷", "a": 160, "b": 4, "ans": 40}, {"op": "÷", "a": 164, "b": 4, "ans": 41}, {"op": "÷", "a": 168, "b": 4, "ans": 42}, {"op": "÷", "a": 172, "b": 4, "ans": 43}, {"op": "÷", "a": 176, "b": 4, "ans": 44}, {"op": "÷", "a": 180, "b": 4, "ans": 45}, {"op": "÷", "a": 184, "b": 4, "ans": 46}, {"op": "÷", "a": 188, "b": 4, "ans": 47}, {"op": "÷", "a": 192, "b": 4, "ans": 48}, {"op": "÷", "a": 196, "b": 4, "ans": 49}, {"op": "÷", "a": 200, "b": 4, "ans": 50}, {"op": "÷", "a": 204, "b": 4, "ans": 51}, {"op": "÷", "a": 208, "b": 4, "ans": 52}, {"op": "÷", "a": 212, "b": 4, "ans": 53}, {"op": "÷", "a": 216, "b": 4, "ans": 54}, {"op": "÷", "a": 220, "b": 4, "ans": 55}, {"op": "÷", "a": 224, "b": 4, "ans": 56}, {"op": "÷", "a": 228, "b": 4, "ans": 57}, {"op": "÷", "a": 232, "b": 4, "ans": 58}, {"op": "÷", "a": 236, "b": 4, "ans": 59}, {"op": "÷", "a": 240, "b": 4, "ans": 60}, {"op": "÷", "a": 244, "b": 4, "ans": 61}, {"op": "÷", "a": 248, "b": 4, "ans": 62}, {"op": "÷", "a": 252, "b": 4, "ans": 63}, {"op": "÷", "a": 256, "b": 4, "ans": 64}, {"op": "÷", "a": 260, "b": 4, "ans": 65}, {"op": "÷", "a": 264, "b": 4, "ans": 66}, {"op": "÷", "a": 268, "b": 4, "ans": 67}, {"op": "÷", "a": 272, "b": 4, "ans": 68}, {"op": "÷", "a": 276, "b": 4, "ans": 69}, {"op": "÷", "a": 280, "b": 4, "ans": 70}, {"op": "÷", "a": 284, "b": 4, "ans": 71}, {"op": "÷", "a": 288, "b": 4, "ans": 72}, {"op": "÷", "a": 292, "b": 4, "ans": 73}, {"op": "÷", "a": 296, "b": 4, "ans": 74}, {"op": "÷", "a": 300, "b": 4, "ans": 75}, {"op": "÷", "a": 304, "b": 4, "ans": 76}, {"op": "÷", "a": 308, "b": 4, "ans": 77}, {"op": "÷", "a": 312, "b": 4, "ans": 78}, {"op": "÷", "a": 316, "b": 4, "ans": 79}, {"op": "÷", "a": 320, "b": 4, "ans": 80}, {"op": "÷", "a": 324, "b": 4, "ans": 81}, {"op": "÷", "a": 328, "b": 4, "ans": 82}, {"op": "÷", "a": 332, "b": 4, "ans": 83}, {"op": "÷", "a": 336, "b": 4, "ans": 84}, {"op": "÷", "a": 340, "b": 4, "ans": 85}, {"op": "÷", "a": 344, "b": 4, "ans": 86}, {"op": "÷", "a": 348, "b": 4, "ans": 87}, {"op": "÷", "a": 352, "b": 4, "ans": 88}, {"op": "÷", "a": 356, "b": 4, "ans": 89}, {"op": "÷", "a": 360, "b": 4, "ans": 90}, {"op": "÷", "a": 364, "b": 4, "ans": 91}, {"op": "÷", "a": 368, "b": 4, "ans": 92}, {"op": "÷", "a": 372, "b": 4, "ans": 93}, {"op": "÷", "a": 376, "b": 4, "ans": 94}, {"op": "÷", "a": 380, "b": 4, "ans": 95}, {"op": "÷", "a": 384, "b": 4, "ans": 96}, {"op": "÷", "a": 388, "b": 4, "ans": 97}, {"op": "÷", "a": 392, "b": 4, "ans": 98}, {"op": "÷", "a": 396, "b": 4, "ans": 99}, {"op": "÷", "a": 400, "b": 4, "ans": 100}, {"op": "÷", "a": 404, "b": 4, "ans": 101}, {"op": "÷", "a": 408, "b": 4, "ans": 102}, {"op": "÷", "a": 412, "b": 4, "ans": 103}, {"op": "÷", "a": 416, "b": 4, "ans": 104}, {"op": "÷", "a": 420, "b": 4, "ans": 105}, {"op": "÷", "a": 424, "b": 4, "ans": 106}, {"op": "÷", "a": 428, "b": 4, "ans": 107}, {"op": "÷", "a": 432, "b": 4, "ans": 108}, {"op": "÷", "a": 436, "b": 4, "ans": 109}, {"op": "÷", "a": 440, "b": 4, "ans": 110}, {"op": "÷", "a": 444, "b": 4, "ans": 111}, {"op": "÷", "a": 448, "b": 4, "ans": 112}, {"op": "÷", "a": 452, "b": 4, "ans": 113}, {"op": "÷", "a": 456, "b": 4, "ans": 114}, {"op": "÷", "a": 460, "b": 4, "ans": 115}, {"op": "÷", "a": 464, "b": 4, "ans": 116}, {"op": "÷", "a": 468, "b": 4, "ans": 117}, {"op": "÷", "a": 472, "b": 4, "ans": 118}, {"op": "÷", "a": 476, "b": 4, "ans": 119}, {"op": "÷", "a": 480, "b": 4, "ans": 120}, {"op": "÷", "a": 484, "b": 4, "ans": 121}, {"op": "÷", "a": 488, "b": 4, "ans": 122}, {"op": "÷", "a": 492, "b": 4, "ans": 123}, {"op": "÷", "a": 496, "b": 4, "ans": 124}, {"op": "÷", "a": 500, "b": 4, "ans": 125}, {"op": "÷", "a": 504, "b": 4, "ans": 126}, {"op": "÷", "a": 508, "b": 4, "ans": 127}, {"op": "÷", "a": 512, "b": 4, "ans": 128}, {"op": "÷", "a": 516, "b": 4, "ans": 129}, {"op": "÷", "a": 520, "b": 4, "ans": 130}, {"op": "÷", "a": 524, "b": 4, "ans": 131}, {"op": "÷", "a": 528, "b": 4, "ans": 132}, {"op": "÷", "a": 532, "b": 4, "ans": 133}, {"op": "÷", "a": 536, "b": 4, "ans": 134}, {"op": "÷", "a": 540, "b": 4, "ans": 135}, {"op": "÷", "a": 544, "b": 4, "ans": 136}, {"op": "÷", "a": 548, "b": 4, "ans": 137}, {"op": "÷", "a": 552, "b": 4, "ans": 138}, {"op": "÷", "a": 556, "b": 4, "ans": 139}, {"op": "÷", "a": 560, "b": 4, "ans": 140}, {"op": "÷", "a": 564, "b": 4, "ans": 141}, {"op": "÷", "a": 568, "b": 4, "ans": 142}, {"op": "÷", "a": 572, "b": 4, "ans": 143}, {"op": "÷", "a": 576, "b": 4, "ans": 144}, {"op": "÷", "a": 580, "b": 4, "ans": 145}, {"op": "÷", "a": 584, "b": 4, "ans": 146}, {"op": "÷", "a": 588, "b": 4, "ans": 147}, {"op": "÷", "a": 592, "b": 4, "ans": 148}, {"op": "÷", "a": 596, "b": 4, "ans": 149}, {"op": "÷", "a": 600, "b": 4, "ans": 150}, {"op": "÷", "a": 604, "b": 4, "ans": 151}, {"op": "÷", "a": 608, "b": 4, "ans": 152}, {"op": "÷", "a": 612, "b": 4, "ans": 153}, {"op": "÷", "a": 616, "b": 4, "ans": 154}, {"op": "÷", "a": 620, "b": 4, "ans": 155}, {"op": "÷", "a": 624, "b": 4, "ans": 156}, {"op": "÷", "a": 628, "b": 4, "ans": 157}, {"op": "÷", "a": 632, "b": 4, "ans": 158}, {"op": "÷", "a": 636, "b": 4, "ans": 159}, {"op": "÷", "a": 640, "b": 4, "ans": 160}, {"op": "÷", "a": 644, "b": 4, "ans": 161}, {"op": "÷", "a": 648, "b": 4, "ans": 162}, {"op": "÷", "a": 652, "b": 4, "ans": 163}, {"op": "÷", "a": 656, "b": 4, "ans": 164}, {"op": "÷", "a": 660, "b": 4, "ans": 165}, {"op": "÷", "a": 664, "b": 4, "ans": 166}, {"op": "÷", "a": 668, "b": 4, "ans": 167}, {"op": "÷", "a": 672, "b": 4, "ans": 168}, {"op": "÷", "a": 676, "b": 4, "ans": 169}, {"op": "÷", "a": 680, "b": 4, "ans": 170}, {"op": "÷", "a": 684, "b": 4, "ans": 171}, {"op": "÷", "a": 688, "b": 4, "ans": 172}, {"op": "÷", "a": 692, "b": 4, "ans": 173}, {"op": "÷", "a": 696, "b": 4, "ans": 174}, {"op": "÷", "a": 700, "b": 4, "ans": 175}, {"op": "÷", "a": 704, "b": 4, "ans": 176}, {"op": "÷", "a": 708, "b": 4, "ans": 177}, {"op": "÷", "a": 712, "b": 4, "ans": 178}, {"op": "÷", "a": 716, "b": 4, "ans": 179}, {"op": "÷", "a": 720, "b": 4, "ans": 180}, {"op": "÷", "a": 724, "b": 4, "ans": 181}, {"op": "÷", "a": 728, "b": 4, "ans": 182}, {"op": "÷", "a": 732, "b": 4, "ans": 183}, {"op": "÷", "a": 736, "b": 4, "ans": 184}, {"op": "÷", "a": 740, "b": 4, "ans": 185}, {"op": "÷", "a": 744, "b": 4, "ans": 186}, {"op": "÷", "a": 748, "b": 4, "ans": 187}, {"op": "÷", "a": 752, "b": 4, "ans": 188}, {"op": "÷", "a": 756, "b": 4, "ans": 189}, {"op": "÷", "a": 760, "b": 4, "ans": 190}, {"op": "÷", "a": 764, "b": 4, "ans": 191}, {"op": "÷", "a": 768, "b": 4, "ans": 192}, {"op": "÷", "a": 772, "b": 4, "ans": 193}, {"op": "÷", "a": 776, "b": 4, "ans": 194}, {"op": "÷", "a": 780, "b": 4, "ans": 195}, {"op": "÷", "a": 784, "b": 4, "ans": 196}, {"op": "÷", "a": 788, "b": 4, "ans": 197}, {"op": "÷", "a": 792, "b": 4, "ans": 198}, {"op": "÷", "a": 796, "b": 4, "ans": 199}, {"op": "÷", "a": 800, "b": 4, "ans": 200}, {"op": "÷", "a": 804, "b": 4, "ans": 201}, {"op": "÷", "a": 808, "b": 4, "ans": 202}, {"op": "÷", "a": 812, "b": 4, "ans": 203}, {"op": "÷", "a": 816, "b": 4, "ans": 204}, {"op": "÷", "a": 820, "b": 4, "ans": 205}, {"op": "÷", "a": 824, "b": 4, "ans": 206}, {"op": "÷", "a": 828, "b": 4, "ans": 207}, {"op": "÷", "a": 832, "b": 4, "ans": 208}, {"op": "÷", "a": 836, "b": 4, "ans": 209}, {"op": "÷", "a": 840, "b": 4, "ans": 210}, {"op": "÷", "a": 844, "b": 4, "ans": 211}, {"op": "÷", "a": 848, "b": 4, "ans": 212}, {"op": "÷", "a": 852, "b": 4, "ans": 213}, {"op": "÷", "a": 856, "b": 4, "ans": 214}, {"op": "÷", "a": 860, "b": 4, "ans": 215}, {"op": "÷", "a": 864, "b": 4, "ans": 216}, {"op": "÷", "a": 868, "b": 4, "ans": 217}, {"op": "÷", "a": 872, "b": 4, "ans": 218}, {"op": "÷", "a": 876, "b": 4, "ans": 219}, {"op": "÷", "a": 880, "b": 4, "ans": 220}, {"op": "÷", "a": 884, "b": 4, "ans": 221}, {"op": "÷", "a": 888, "b": 4, "ans": 222}, {"op": "÷", "a": 892, "b": 4, "ans": 223}, {"op": "÷", "a": 896, "b": 4, "ans": 224}, {"op": "÷", "a": 900, "b": 4, "ans": 225}, {"op": "÷", "a": 904, "b": 4, "ans": 226}, {"op": "÷", "a": 908, "b": 4, "ans": 227}, {"op": "÷", "a": 912, "b": 4, "ans": 228}, {"op": "÷", "a": 916, "b": 4, "ans": 229}, {"op": "÷", "a": 920, "b": 4, "ans": 230}, {"op": "÷", "a": 924, "b": 4, "ans": 231}, {"op": "÷", "a": 928, "b": 4, "ans": 232}, {"op": "÷", "a": 932, "b": 4, "ans": 233}, {"op": "÷", "a": 936, "b": 4, "ans": 234}, {"op": "÷", "a": 940, "b": 4, "ans": 235}, {"op": "÷", "a": 944, "b": 4, "ans": 236}, {"op": "÷", "a": 948, "b": 4, "ans": 237}, {"op": "÷", "a": 952, "b": 4, "ans": 238}, {"op": "÷", "a": 956, "b": 4, "ans": 239}, {"op": "÷", "a": 960, "b": 4, "ans": 240}, {"op": "÷", "a": 964, "b": 4, "ans": 241}, {"op": "÷", "a": 968, "b": 4, "ans": 242}, {"op": "÷", "a": 972, "b": 4, "ans": 243}, {"op": "÷", "a": 976, "b": 4, "ans": 244}, {"op": "÷", "a": 980, "b": 4, "ans": 245}, {"op": "÷", "a": 984, "b": 4, "ans": 246}, {"op": "÷", "a": 988, "b": 4, "ans": 247}, {"op": "÷", "a": 992, "b": 4, "ans": 248}, {"op": "÷", "a": 996, "b": 4, "ans": 249}, {"op": "÷", "a": 100, "b": 5, "ans": 20}, {"op": "÷", "a": 105, "b": 5, "ans": 21}, {"op": "÷", "a": 110, "b": 5, "ans": 22}, {"op": "÷", "a": 115, "b": 5, "ans": 23}, {"op": "÷", "a": 120, "b": 5, "ans": 24}, {"op": "÷", "a": 125, "b": 5, "ans": 25}, {"op": "÷", "a": 130, "b": 5, "ans": 26}, {"op": "÷", "a": 135, "b": 5, "ans": 27}, {"op": "÷", "a": 140, "b": 5, "ans": 28}, {"op": "÷", "a": 145, "b": 5, "ans": 29}, {"op": "÷", "a": 150, "b": 5, "ans": 30}, {"op": "÷", "a": 155, "b": 5, "ans": 31}, {"op": "÷", "a": 160, "b": 5, "ans": 32}, {"op": "÷", "a": 165, "b": 5, "ans": 33}, {"op": "÷", "a": 170, "b": 5, "ans": 34}, {"op": "÷", "a": 175, "b": 5, "ans": 35}, {"op": "÷", "a": 180, "b": 5, "ans": 36}, {"op": "÷", "a": 185, "b": 5, "ans": 37}, {"op": "÷", "a": 190, "b": 5, "ans": 38}, {"op": "÷", "a": 195, "b": 5, "ans": 39}, {"op": "÷", "a": 200, "b": 5, "ans": 40}, {"op": "÷", "a": 205, "b": 5, "ans": 41}, {"op": "÷", "a": 210, "b": 5, "ans": 42}, {"op": "÷", "a": 215, "b": 5, "ans": 43}, {"op": "÷", "a": 220, "b": 5, "ans": 44}, {"op": "÷", "a": 225, "b": 5, "ans": 45}, {"op": "÷", "a": 230, "b": 5, "ans": 46}, {"op": "÷", "a": 235, "b": 5, "ans": 47}, {"op": "÷", "a": 240, "b": 5, "ans": 48}, {"op": "÷", "a": 245, "b": 5, "ans": 49}, {"op": "÷", "a": 250, "b": 5, "ans": 50}, {"op": "÷", "a": 255, "b": 5, "ans": 51}, {"op": "÷", "a": 260, "b": 5, "ans": 52}, {"op": "÷", "a": 265, "b": 5, "ans": 53}, {"op": "÷", "a": 270, "b": 5, "ans": 54}, {"op": "÷", "a": 275, "b": 5, "ans": 55}, {"op": "÷", "a": 280, "b": 5, "ans": 56}, {"op": "÷", "a": 285, "b": 5, "ans": 57}, {"op": "÷", "a": 290, "b": 5, "ans": 58}, {"op": "÷", "a": 295, "b": 5, "ans": 59}, {"op": "÷", "a": 300, "b": 5, "ans": 60}, {"op": "÷", "a": 305, "b": 5, "ans": 61}, {"op": "÷", "a": 310, "b": 5, "ans": 62}, {"op": "÷", "a": 315, "b": 5, "ans": 63}, {"op": "÷", "a": 320, "b": 5, "ans": 64}, {"op": "÷", "a": 325, "b": 5, "ans": 65}, {"op": "÷", "a": 330, "b": 5, "ans": 66}, {"op": "÷", "a": 335, "b": 5, "ans": 67}, {"op": "÷", "a": 340, "b": 5, "ans": 68}, {"op": "÷", "a": 345, "b": 5, "ans": 69}, {"op": "÷", "a": 350, "b": 5, "ans": 70}, {"op": "÷", "a": 355, "b": 5, "ans": 71}, {"op": "÷", "a": 360, "b": 5, "ans": 72}, {"op": "÷", "a": 365, "b": 5, "ans": 73}, {"op": "÷", "a": 370, "b": 5, "ans": 74}, {"op": "÷", "a": 375, "b": 5, "ans": 75}, {"op": "÷", "a": 380, "b": 5, "ans": 76}, {"op": "÷", "a": 385, "b": 5, "ans": 77}, {"op": "÷", "a": 390, "b": 5, "ans": 78}, {"op": "÷", "a": 395, "b": 5, "ans": 79}, {"op": "÷", "a": 400, "b": 5, "ans": 80}, {"op": "÷", "a": 405, "b": 5, "ans": 81}, {"op": "÷", "a": 410, "b": 5, "ans": 82}, {"op": "÷", "a": 415, "b": 5, "ans": 83}, {"op": "÷", "a": 420, "b": 5, "ans": 84}, {"op": "÷", "a": 425, "b": 5, "ans": 85}, {"op": "÷", "a": 430, "b": 5, "ans": 86}, {"op": "÷", "a": 435, "b": 5, "ans": 87}, {"op": "÷", "a": 440, "b": 5, "ans": 88}, {"op": "÷", "a": 445, "b": 5, "ans": 89}, {"op": "÷", "a": 450, "b": 5, "ans": 90}, {"op": "÷", "a": 455, "b": 5, "ans": 91}, {"op": "÷", "a": 460, "b": 5, "ans": 92}, {"op": "÷", "a": 465, "b": 5, "ans": 93}, {"op": "÷", "a": 470, "b": 5, "ans": 94}, {"op": "÷", "a": 475, "b": 5, "ans": 95}, {"op": "÷", "a": 480, "b": 5, "ans": 96}, {"op": "÷", "a": 485, "b": 5, "ans": 97}, {"op": "÷", "a": 490, "b": 5, "ans": 98}, {"op": "÷", "a": 495, "b": 5, "ans": 99}, {"op": "÷", "a": 500, "b": 5, "ans": 100}, {"op": "÷", "a": 505, "b": 5, "ans": 101}, {"op": "÷", "a": 510, "b": 5, "ans": 102}, {"op": "÷", "a": 515, "b": 5, "ans": 103}, {"op": "÷", "a": 520, "b": 5, "ans": 104}, {"op": "÷", "a": 525, "b": 5, "ans": 105}, {"op": "÷", "a": 530, "b": 5, "ans": 106}, {"op": "÷", "a": 535, "b": 5, "ans": 107}, {"op": "÷", "a": 540, "b": 5, "ans": 108}, {"op": "÷", "a": 545, "b": 5, "ans": 109}, {"op": "÷", "a": 550, "b": 5, "ans": 110}, {"op": "÷", "a": 555, "b": 5, "ans": 111}, {"op": "÷", "a": 560, "b": 5, "ans": 112}, {"op": "÷", "a": 565, "b": 5, "ans": 113}, {"op": "÷", "a": 570, "b": 5, "ans": 114}, {"op": "÷", "a": 575, "b": 5, "ans": 115}, {"op": "÷", "a": 580, "b": 5, "ans": 116}, {"op": "÷", "a": 585, "b": 5, "ans": 117}, {"op": "÷", "a": 590, "b": 5, "ans": 118}, {"op": "÷", "a": 595, "b": 5, "ans": 119}, {"op": "÷", "a": 600, "b": 5, "ans": 120}, {"op": "÷", "a": 605, "b": 5, "ans": 121}, {"op": "÷", "a": 610, "b": 5, "ans": 122}, {"op": "÷", "a": 615, "b": 5, "ans": 123}, {"op": "÷", "a": 620, "b": 5, "ans": 124}, {"op": "÷", "a": 625, "b": 5, "ans": 125}, {"op": "÷", "a": 630, "b": 5, "ans": 126}, {"op": "÷", "a": 635, "b": 5, "ans": 127}, {"op": "÷", "a": 640, "b": 5, "ans": 128}, {"op": "÷", "a": 645, "b": 5, "ans": 129}, {"op": "÷", "a": 650, "b": 5, "ans": 130}, {"op": "÷", "a": 655, "b": 5, "ans": 131}, {"op": "÷", "a": 660, "b": 5, "ans": 132}, {"op": "÷", "a": 665, "b": 5, "ans": 133}, {"op": "÷", "a": 670, "b": 5, "ans": 134}, {"op": "÷", "a": 675, "b": 5, "ans": 135}, {"op": "÷", "a": 680, "b": 5, "ans": 136}, {"op": "÷", "a": 685, "b": 5, "ans": 137}, {"op": "÷", "a": 690, "b": 5, "ans": 138}, {"op": "÷", "a": 695, "b": 5, "ans": 139}, {"op": "÷", "a": 700, "b": 5, "ans": 140}, {"op": "÷", "a": 705, "b": 5, "ans": 141}, {"op": "÷", "a": 710, "b": 5, "ans": 142}, {"op": "÷", "a": 715, "b": 5, "ans": 143}, {"op": "÷", "a": 720, "b": 5, "ans": 144}, {"op": "÷", "a": 725, "b": 5, "ans": 145}, {"op": "÷", "a": 730, "b": 5, "ans": 146}, {"op": "÷", "a": 735, "b": 5, "ans": 147}, {"op": "÷", "a": 740, "b": 5, "ans": 148}, {"op": "÷", "a": 745, "b": 5, "ans": 149}, {"op": "÷", "a": 750, "b": 5, "ans": 150}, {"op": "÷", "a": 755, "b": 5, "ans": 151}, {"op": "÷", "a": 760, "b": 5, "ans": 152}, {"op": "÷", "a": 765, "b": 5, "ans": 153}, {"op": "÷", "a": 770, "b": 5, "ans": 154}, {"op": "÷", "a": 775, "b": 5, "ans": 155}, {"op": "÷", "a": 780, "b": 5, "ans": 156}, {"op": "÷", "a": 785, "b": 5, "ans": 157}, {"op": "÷", "a": 790, "b": 5, "ans": 158}, {"op": "÷", "a": 795, "b": 5, "ans": 159}, {"op": "÷", "a": 800, "b": 5, "ans": 160}, {"op": "÷", "a": 805, "b": 5, "ans": 161}, {"op": "÷", "a": 810, "b": 5, "ans": 162}, {"op": "÷", "a": 815, "b": 5, "ans": 163}, {"op": "÷", "a": 820, "b": 5, "ans": 164}, {"op": "÷", "a": 825, "b": 5, "ans": 165}, {"op": "÷", "a": 830, "b": 5, "ans": 166}, {"op": "÷", "a": 835, "b": 5, "ans": 167}, {"op": "÷", "a": 840, "b": 5, "ans": 168}, {"op": "÷", "a": 845, "b": 5, "ans": 169}, {"op": "÷", "a": 850, "b": 5, "ans": 170}, {"op": "÷", "a": 855, "b": 5, "ans": 171}, {"op": "÷", "a": 860, "b": 5, "ans": 172}, {"op": "÷", "a": 865, "b": 5, "ans": 173}, {"op": "÷", "a": 870, "b": 5, "ans": 174}, {"op": "÷", "a": 875, "b": 5, "ans": 175}, {"op": "÷", "a": 880, "b": 5, "ans": 176}, {"op": "÷", "a": 885, "b": 5, "ans": 177}, {"op": "÷", "a": 890, "b": 5, "ans": 178}, {"op": "÷", "a": 895, "b": 5, "ans": 179}, {"op": "÷", "a": 900, "b": 5, "ans": 180}, {"op": "÷", "a": 905, "b": 5, "ans": 181}, {"op": "÷", "a": 910, "b": 5, "ans": 182}, {"op": "÷", "a": 915, "b": 5, "ans": 183}, {"op": "÷", "a": 920, "b": 5, "ans": 184}, {"op": "÷", "a": 925, "b": 5, "ans": 185}, {"op": "÷", "a": 930, "b": 5, "ans": 186}, {"op": "÷", "a": 935, "b": 5, "ans": 187}, {"op": "÷", "a": 940, "b": 5, "ans": 188}, {"op": "÷", "a": 945, "b": 5, "ans": 189}, {"op": "÷", "a": 950, "b": 5, "ans": 190}, {"op": "÷", "a": 955, "b": 5, "ans": 191}, {"op": "÷", "a": 960, "b": 5, "ans": 192}, {"op": "÷", "a": 965, "b": 5, "ans": 193}, {"op": "÷", "a": 970, "b": 5, "ans": 194}, {"op": "÷", "a": 975, "b": 5, "ans": 195}, {"op": "÷", "a": 980, "b": 5, "ans": 196}, {"op": "÷", "a": 985, "b": 5, "ans": 197}, {"op": "÷", "a": 990, "b": 5, "ans": 198}, {"op": "÷", "a": 995, "b": 5, "ans": 199}, {"op": "÷", "a": 102, "b": 6, "ans": 17}, {"op": "÷", "a": 108, "b": 6, "ans": 18}, {"op": "÷", "a": 114, "b": 6, "ans": 19}, {"op": "÷", "a": 120, "b": 6, "ans": 20}, {"op": "÷", "a": 126, "b": 6, "ans": 21}, {"op": "÷", "a": 132, "b": 6, "ans": 22}, {"op": "÷", "a": 138, "b": 6, "ans": 23}, {"op": "÷", "a": 144, "b": 6, "ans": 24}, {"op": "÷", "a": 150, "b": 6, "ans": 25}, {"op": "÷", "a": 156, "b": 6, "ans": 26}, {"op": "÷", "a": 162, "b": 6, "ans": 27}, {"op": "÷", "a": 168, "b": 6, "ans": 28}, {"op": "÷", "a": 174, "b": 6, "ans": 29}, {"op": "÷", "a": 180, "b": 6, "ans": 30}, {"op": "÷", "a": 186, "b": 6, "ans": 31}, {"op": "÷", "a": 192, "b": 6, "ans": 32}, {"op": "÷", "a": 198, "b": 6, "ans": 33}, {"op": "÷", "a": 204, "b": 6, "ans": 34}, {"op": "÷", "a": 210, "b": 6, "ans": 35}, {"op": "÷", "a": 216, "b": 6, "ans": 36}, {"op": "÷", "a": 222, "b": 6, "ans": 37}, {"op": "÷", "a": 228, "b": 6, "ans": 38}, {"op": "÷", "a": 234, "b": 6, "ans": 39}, {"op": "÷", "a": 240, "b": 6, "ans": 40}, {"op": "÷", "a": 246, "b": 6, "ans": 41}, {"op": "÷", "a": 252, "b": 6, "ans": 42}, {"op": "÷", "a": 258, "b": 6, "ans": 43}, {"op": "÷", "a": 264, "b": 6, "ans": 44}, {"op": "÷", "a": 270, "b": 6, "ans": 45}, {"op": "÷", "a": 276, "b": 6, "ans": 46}, {"op": "÷", "a": 282, "b": 6, "ans": 47}, {"op": "÷", "a": 288, "b": 6, "ans": 48}, {"op": "÷", "a": 294, "b": 6, "ans": 49}, {"op": "÷", "a": 300, "b": 6, "ans": 50}, {"op": "÷", "a": 306, "b": 6, "ans": 51}, {"op": "÷", "a": 312, "b": 6, "ans": 52}, {"op": "÷", "a": 318, "b": 6, "ans": 53}, {"op": "÷", "a": 324, "b": 6, "ans": 54}, {"op": "÷", "a": 330, "b": 6, "ans": 55}, {"op": "÷", "a": 336, "b": 6, "ans": 56}, {"op": "÷", "a": 342, "b": 6, "ans": 57}, {"op": "÷", "a": 348, "b": 6, "ans": 58}, {"op": "÷", "a": 354, "b": 6, "ans": 59}, {"op": "÷", "a": 360, "b": 6, "ans": 60}, {"op": "÷", "a": 366, "b": 6, "ans": 61}, {"op": "÷", "a": 372, "b": 6, "ans": 62}, {"op": "÷", "a": 378, "b": 6, "ans": 63}, {"op": "÷", "a": 384, "b": 6, "ans": 64}, {"op": "÷", "a": 390, "b": 6, "ans": 65}, {"op": "÷", "a": 396, "b": 6, "ans": 66}, {"op": "÷", "a": 402, "b": 6, "ans": 67}, {"op": "÷", "a": 408, "b": 6, "ans": 68}, {"op": "÷", "a": 414, "b": 6, "ans": 69}, {"op": "÷", "a": 420, "b": 6, "ans": 70}, {"op": "÷", "a": 426, "b": 6, "ans": 71}, {"op": "÷", "a": 432, "b": 6, "ans": 72}, {"op": "÷", "a": 438, "b": 6, "ans": 73}, {"op": "÷", "a": 444, "b": 6, "ans": 74}, {"op": "÷", "a": 450, "b": 6, "ans": 75}, {"op": "÷", "a": 456, "b": 6, "ans": 76}, {"op": "÷", "a": 462, "b": 6, "ans": 77}, {"op": "÷", "a": 468, "b": 6, "ans": 78}, {"op": "÷", "a": 474, "b": 6, "ans": 79}, {"op": "÷", "a": 480, "b": 6, "ans": 80}, {"op": "÷", "a": 486, "b": 6, "ans": 81}, {"op": "÷", "a": 492, "b": 6, "ans": 82}, {"op": "÷", "a": 498, "b": 6, "ans": 83}, {"op": "÷", "a": 504, "b": 6, "ans": 84}, {"op": "÷", "a": 510, "b": 6, "ans": 85}, {"op": "÷", "a": 516, "b": 6, "ans": 86}, {"op": "÷", "a": 522, "b": 6, "ans": 87}, {"op": "÷", "a": 528, "b": 6, "ans": 88}, {"op": "÷", "a": 534, "b": 6, "ans": 89}, {"op": "÷", "a": 540, "b": 6, "ans": 90}, {"op": "÷", "a": 546, "b": 6, "ans": 91}, {"op": "÷", "a": 552, "b": 6, "ans": 92}, {"op": "÷", "a": 558, "b": 6, "ans": 93}, {"op": "÷", "a": 564, "b": 6, "ans": 94}, {"op": "÷", "a": 570, "b": 6, "ans": 95}, {"op": "÷", "a": 576, "b": 6, "ans": 96}, {"op": "÷", "a": 582, "b": 6, "ans": 97}, {"op": "÷", "a": 588, "b": 6, "ans": 98}, {"op": "÷", "a": 594, "b": 6, "ans": 99}, {"op": "÷", "a": 600, "b": 6, "ans": 100}, {"op": "÷", "a": 606, "b": 6, "ans": 101}, {"op": "÷", "a": 612, "b": 6, "ans": 102}, {"op": "÷", "a": 618, "b": 6, "ans": 103}, {"op": "÷", "a": 624, "b": 6, "ans": 104}, {"op": "÷", "a": 630, "b": 6, "ans": 105}, {"op": "÷", "a": 636, "b": 6, "ans": 106}, {"op": "÷", "a": 642, "b": 6, "ans": 107}, {"op": "÷", "a": 648, "b": 6, "ans": 108}, {"op": "÷", "a": 654, "b": 6, "ans": 109}, {"op": "÷", "a": 660, "b": 6, "ans": 110}, {"op": "÷", "a": 666, "b": 6, "ans": 111}, {"op": "÷", "a": 672, "b": 6, "ans": 112}, {"op": "÷", "a": 678, "b": 6, "ans": 113}, {"op": "÷", "a": 684, "b": 6, "ans": 114}, {"op": "÷", "a": 690, "b": 6, "ans": 115}, {"op": "÷", "a": 696, "b": 6, "ans": 116}, {"op": "÷", "a": 702, "b": 6, "ans": 117}, {"op": "÷", "a": 708, "b": 6, "ans": 118}, {"op": "÷", "a": 714, "b": 6, "ans": 119}, {"op": "÷", "a": 720, "b": 6, "ans": 120}, {"op": "÷", "a": 726, "b": 6, "ans": 121}, {"op": "÷", "a": 732, "b": 6, "ans": 122}, {"op": "÷", "a": 738, "b": 6, "ans": 123}, {"op": "÷", "a": 744, "b": 6, "ans": 124}, {"op": "÷", "a": 750, "b": 6, "ans": 125}, {"op": "÷", "a": 756, "b": 6, "ans": 126}, {"op": "÷", "a": 762, "b": 6, "ans": 127}, {"op": "÷", "a": 768, "b": 6, "ans": 128}, {"op": "÷", "a": 774, "b": 6, "ans": 129}, {"op": "÷", "a": 780, "b": 6, "ans": 130}, {"op": "÷", "a": 786, "b": 6, "ans": 131}, {"op": "÷", "a": 792, "b": 6, "ans": 132}, {"op": "÷", "a": 798, "b": 6, "ans": 133}, {"op": "÷", "a": 804, "b": 6, "ans": 134}, {"op": "÷", "a": 810, "b": 6, "ans": 135}, {"op": "÷", "a": 816, "b": 6, "ans": 136}, {"op": "÷", "a": 822, "b": 6, "ans": 137}, {"op": "÷", "a": 828, "b": 6, "ans": 138}, {"op": "÷", "a": 834, "b": 6, "ans": 139}, {"op": "÷", "a": 840, "b": 6, "ans": 140}, {"op": "÷", "a": 846, "b": 6, "ans": 141}, {"op": "÷", "a": 852, "b": 6, "ans": 142}, {"op": "÷", "a": 858, "b": 6, "ans": 143}, {"op": "÷", "a": 864, "b": 6, "ans": 144}, {"op": "÷", "a": 870, "b": 6, "ans": 145}, {"op": "÷", "a": 876, "b": 6, "ans": 146}, {"op": "÷", "a": 882, "b": 6, "ans": 147}, {"op": "÷", "a": 888, "b": 6, "ans": 148}, {"op": "÷", "a": 894, "b": 6, "ans": 149}, {"op": "÷", "a": 900, "b": 6, "ans": 150}, {"op": "÷", "a": 906, "b": 6, "ans": 151}, {"op": "÷", "a": 912, "b": 6, "ans": 152}, {"op": "÷", "a": 918, "b": 6, "ans": 153}, {"op": "÷", "a": 924, "b": 6, "ans": 154}, {"op": "÷", "a": 930, "b": 6, "ans": 155}, {"op": "÷", "a": 936, "b": 6, "ans": 156}, {"op": "÷", "a": 942, "b": 6, "ans": 157}, {"op": "÷", "a": 948, "b": 6, "ans": 158}, {"op": "÷", "a": 954, "b": 6, "ans": 159}, {"op": "÷", "a": 960, "b": 6, "ans": 160}, {"op": "÷", "a": 966, "b": 6, "ans": 161}, {"op": "÷", "a": 972, "b": 6, "ans": 162}, {"op": "÷", "a": 978, "b": 6, "ans": 163}, {"op": "÷", "a": 984, "b": 6, "ans": 164}, {"op": "÷", "a": 990, "b": 6, "ans": 165}, {"op": "÷", "a": 996, "b": 6, "ans": 166}, {"op": "÷", "a": 105, "b": 7, "ans": 15}, {"op": "÷", "a": 112, "b": 7, "ans": 16}, {"op": "÷", "a": 119, "b": 7, "ans": 17}, {"op": "÷", "a": 126, "b": 7, "ans": 18}, {"op": "÷", "a": 133, "b": 7, "ans": 19}, {"op": "÷", "a": 140, "b": 7, "ans": 20}, {"op": "÷", "a": 147, "b": 7, "ans": 21}, {"op": "÷", "a": 154, "b": 7, "ans": 22}, {"op": "÷", "a": 161, "b": 7, "ans": 23}, {"op": "÷", "a": 168, "b": 7, "ans": 24}, {"op": "÷", "a": 175, "b": 7, "ans": 25}, {"op": "÷", "a": 182, "b": 7, "ans": 26}, {"op": "÷", "a": 189, "b": 7, "ans": 27}, {"op": "÷", "a": 196, "b": 7, "ans": 28}, {"op": "÷", "a": 203, "b": 7, "ans": 29}, {"op": "÷", "a": 210, "b": 7, "ans": 30}, {"op": "÷", "a": 217, "b": 7, "ans": 31}, {"op": "÷", "a": 224, "b": 7, "ans": 32}, {"op": "÷", "a": 231, "b": 7, "ans": 33}, {"op": "÷", "a": 238, "b": 7, "ans": 34}, {"op": "÷", "a": 245, "b": 7, "ans": 35}, {"op": "÷", "a": 252, "b": 7, "ans": 36}, {"op": "÷", "a": 259, "b": 7, "ans": 37}, {"op": "÷", "a": 266, "b": 7, "ans": 38}, {"op": "÷", "a": 273, "b": 7, "ans": 39}, {"op": "÷", "a": 280, "b": 7, "ans": 40}, {"op": "÷", "a": 287, "b": 7, "ans": 41}, {"op": "÷", "a": 294, "b": 7, "ans": 42}, {"op": "÷", "a": 301, "b": 7, "ans": 43}, {"op": "÷", "a": 308, "b": 7, "ans": 44}, {"op": "÷", "a": 315, "b": 7, "ans": 45}, {"op": "÷", "a": 322, "b": 7, "ans": 46}, {"op": "÷", "a": 329, "b": 7, "ans": 47}, {"op": "÷", "a": 336, "b": 7, "ans": 48}, {"op": "÷", "a": 343, "b": 7, "ans": 49}, {"op": "÷", "a": 350, "b": 7, "ans": 50}, {"op": "÷", "a": 357, "b": 7, "ans": 51}, {"op": "÷", "a": 364, "b": 7, "ans": 52}, {"op": "÷", "a": 371, "b": 7, "ans": 53}, {"op": "÷", "a": 378, "b": 7, "ans": 54}, {"op": "÷", "a": 385, "b": 7, "ans": 55}, {"op": "÷", "a": 392, "b": 7, "ans": 56}, {"op": "÷", "a": 399, "b": 7, "ans": 57}, {"op": "÷", "a": 406, "b": 7, "ans": 58}, {"op": "÷", "a": 413, "b": 7, "ans": 59}, {"op": "÷", "a": 420, "b": 7, "ans": 60}, {"op": "÷", "a": 427, "b": 7, "ans": 61}, {"op": "÷", "a": 434, "b": 7, "ans": 62}, {"op": "÷", "a": 441, "b": 7, "ans": 63}, {"op": "÷", "a": 448, "b": 7, "ans": 64}, {"op": "÷", "a": 455, "b": 7, "ans": 65}, {"op": "÷", "a": 462, "b": 7, "ans": 66}, {"op": "÷", "a": 469, "b": 7, "ans": 67}, {"op": "÷", "a": 476, "b": 7, "ans": 68}, {"op": "÷", "a": 483, "b": 7, "ans": 69}, {"op": "÷", "a": 490, "b": 7, "ans": 70}, {"op": "÷", "a": 497, "b": 7, "ans": 71}, {"op": "÷", "a": 504, "b": 7, "ans": 72}, {"op": "÷", "a": 511, "b": 7, "ans": 73}, {"op": "÷", "a": 518, "b": 7, "ans": 74}, {"op": "÷", "a": 525, "b": 7, "ans": 75}, {"op": "÷", "a": 532, "b": 7, "ans": 76}, {"op": "÷", "a": 539, "b": 7, "ans": 77}, {"op": "÷", "a": 546, "b": 7, "ans": 78}, {"op": "÷", "a": 553, "b": 7, "ans": 79}, {"op": "÷", "a": 560, "b": 7, "ans": 80}, {"op": "÷", "a": 567, "b": 7, "ans": 81}, {"op": "÷", "a": 574, "b": 7, "ans": 82}, {"op": "÷", "a": 581, "b": 7, "ans": 83}, {"op": "÷", "a": 588, "b": 7, "ans": 84}, {"op": "÷", "a": 595, "b": 7, "ans": 85}, {"op": "÷", "a": 602, "b": 7, "ans": 86}, {"op": "÷", "a": 609, "b": 7, "ans": 87}, {"op": "÷", "a": 616, "b": 7, "ans": 88}, {"op": "÷", "a": 623, "b": 7, "ans": 89}, {"op": "÷", "a": 630, "b": 7, "ans": 90}, {"op": "÷", "a": 637, "b": 7, "ans": 91}, {"op": "÷", "a": 644, "b": 7, "ans": 92}, {"op": "÷", "a": 651, "b": 7, "ans": 93}, {"op": "÷", "a": 658, "b": 7, "ans": 94}, {"op": "÷", "a": 665, "b": 7, "ans": 95}, {"op": "÷", "a": 672, "b": 7, "ans": 96}, {"op": "÷", "a": 679, "b": 7, "ans": 97}, {"op": "÷", "a": 686, "b": 7, "ans": 98}, {"op": "÷", "a": 693, "b": 7, "ans": 99}, {"op": "÷", "a": 700, "b": 7, "ans": 100}, {"op": "÷", "a": 707, "b": 7, "ans": 101}, {"op": "÷", "a": 714, "b": 7, "ans": 102}, {"op": "÷", "a": 721, "b": 7, "ans": 103}, {"op": "÷", "a": 728, "b": 7, "ans": 104}, {"op": "÷", "a": 735, "b": 7, "ans": 105}, {"op": "÷", "a": 742, "b": 7, "ans": 106}, {"op": "÷", "a": 749, "b": 7, "ans": 107}, {"op": "÷", "a": 756, "b": 7, "ans": 108}, {"op": "÷", "a": 763, "b": 7, "ans": 109}, {"op": "÷", "a": 770, "b": 7, "ans": 110}, {"op": "÷", "a": 777, "b": 7, "ans": 111}, {"op": "÷", "a": 784, "b": 7, "ans": 112}, {"op": "÷", "a": 791, "b": 7, "ans": 113}, {"op": "÷", "a": 798, "b": 7, "ans": 114}, {"op": "÷", "a": 805, "b": 7, "ans": 115}, {"op": "÷", "a": 812, "b": 7, "ans": 116}, {"op": "÷", "a": 819, "b": 7, "ans": 117}, {"op": "÷", "a": 826, "b": 7, "ans": 118}, {"op": "÷", "a": 833, "b": 7, "ans": 119}, {"op": "÷", "a": 840, "b": 7, "ans": 120}, {"op": "÷", "a": 847, "b": 7, "ans": 121}, {"op": "÷", "a": 854, "b": 7, "ans": 122}, {"op": "÷", "a": 861, "b": 7, "ans": 123}, {"op": "÷", "a": 868, "b": 7, "ans": 124}, {"op": "÷", "a": 875, "b": 7, "ans": 125}, {"op": "÷", "a": 882, "b": 7, "ans": 126}, {"op": "÷", "a": 889, "b": 7, "ans": 127}, {"op": "÷", "a": 896, "b": 7, "ans": 128}, {"op": "÷", "a": 903, "b": 7, "ans": 129}, {"op": "÷", "a": 910, "b": 7, "ans": 130}, {"op": "÷", "a": 917, "b": 7, "ans": 131}, {"op": "÷", "a": 924, "b": 7, "ans": 132}, {"op": "÷", "a": 931, "b": 7, "ans": 133}, {"op": "÷", "a": 938, "b": 7, "ans": 134}, {"op": "÷", "a": 945, "b": 7, "ans": 135}, {"op": "÷", "a": 952, "b": 7, "ans": 136}, {"op": "÷", "a": 959, "b": 7, "ans": 137}, {"op": "÷", "a": 966, "b": 7, "ans": 138}, {"op": "÷", "a": 973, "b": 7, "ans": 139}, {"op": "÷", "a": 980, "b": 7, "ans": 140}, {"op": "÷", "a": 987, "b": 7, "ans": 141}, {"op": "÷", "a": 994, "b": 7, "ans": 142}, {"op": "÷", "a": 104, "b": 8, "ans": 13}, {"op": "÷", "a": 112, "b": 8, "ans": 14}, {"op": "÷", "a": 120, "b": 8, "ans": 15}, {"op": "÷", "a": 128, "b": 8, "ans": 16}, {"op": "÷", "a": 136, "b": 8, "ans": 17}, {"op": "÷", "a": 144, "b": 8, "ans": 18}, {"op": "÷", "a": 152, "b": 8, "ans": 19}, {"op": "÷", "a": 160, "b": 8, "ans": 20}, {"op": "÷", "a": 168, "b": 8, "ans": 21}, {"op": "÷", "a": 176, "b": 8, "ans": 22}, {"op": "÷", "a": 184, "b": 8, "ans": 23}, {"op": "÷", "a": 192, "b": 8, "ans": 24}, {"op": "÷", "a": 200, "b": 8, "ans": 25}, {"op": "÷", "a": 208, "b": 8, "ans": 26}, {"op": "÷", "a": 216, "b": 8, "ans": 27}, {"op": "÷", "a": 224, "b": 8, "ans": 28}, {"op": "÷", "a": 232, "b": 8, "ans": 29}, {"op": "÷", "a": 240, "b": 8, "ans": 30}, {"op": "÷", "a": 248, "b": 8, "ans": 31}, {"op": "÷", "a": 256, "b": 8, "ans": 32}, {"op": "÷", "a": 264, "b": 8, "ans": 33}, {"op": "÷", "a": 272, "b": 8, "ans": 34}, {"op": "÷", "a": 280, "b": 8, "ans": 35}, {"op": "÷", "a": 288, "b": 8, "ans": 36}, {"op": "÷", "a": 296, "b": 8, "ans": 37}, {"op": "÷", "a": 304, "b": 8, "ans": 38}, {"op": "÷", "a": 312, "b": 8, "ans": 39}, {"op": "÷", "a": 320, "b": 8, "ans": 40}, {"op": "÷", "a": 328, "b": 8, "ans": 41}, {"op": "÷", "a": 336, "b": 8, "ans": 42}, {"op": "÷", "a": 344, "b": 8, "ans": 43}, {"op": "÷", "a": 352, "b": 8, "ans": 44}, {"op": "÷", "a": 360, "b": 8, "ans": 45}, {"op": "÷", "a": 368, "b": 8, "ans": 46}, {"op": "÷", "a": 376, "b": 8, "ans": 47}, {"op": "÷", "a": 384, "b": 8, "ans": 48}, {"op": "÷", "a": 392, "b": 8, "ans": 49}, {"op": "÷", "a": 400, "b": 8, "ans": 50}, {"op": "÷", "a": 408, "b": 8, "ans": 51}, {"op": "÷", "a": 416, "b": 8, "ans": 52}, {"op": "÷", "a": 424, "b": 8, "ans": 53}, {"op": "÷", "a": 432, "b": 8, "ans": 54}, {"op": "÷", "a": 440, "b": 8, "ans": 55}, {"op": "÷", "a": 448, "b": 8, "ans": 56}, {"op": "÷", "a": 456, "b": 8, "ans": 57}, {"op": "÷", "a": 464, "b": 8, "ans": 58}, {"op": "÷", "a": 472, "b": 8, "ans": 59}, {"op": "÷", "a": 480, "b": 8, "ans": 60}, {"op": "÷", "a": 488, "b": 8, "ans": 61}, {"op": "÷", "a": 496, "b": 8, "ans": 62}, {"op": "÷", "a": 504, "b": 8, "ans": 63}, {"op": "÷", "a": 512, "b": 8, "ans": 64}, {"op": "÷", "a": 520, "b": 8, "ans": 65}, {"op": "÷", "a": 528, "b": 8, "ans": 66}, {"op": "÷", "a": 536, "b": 8, "ans": 67}, {"op": "÷", "a": 544, "b": 8, "ans": 68}, {"op": "÷", "a": 552, "b": 8, "ans": 69}, {"op": "÷", "a": 560, "b": 8, "ans": 70}, {"op": "÷", "a": 568, "b": 8, "ans": 71}, {"op": "÷", "a": 576, "b": 8, "ans": 72}, {"op": "÷", "a": 584, "b": 8, "ans": 73}, {"op": "÷", "a": 592, "b": 8, "ans": 74}, {"op": "÷", "a": 600, "b": 8, "ans": 75}, {"op": "÷", "a": 608, "b": 8, "ans": 76}, {"op": "÷", "a": 616, "b": 8, "ans": 77}, {"op": "÷", "a": 624, "b": 8, "ans": 78}, {"op": "÷", "a": 632, "b": 8, "ans": 79}, {"op": "÷", "a": 640, "b": 8, "ans": 80}, {"op": "÷", "a": 648, "b": 8, "ans": 81}, {"op": "÷", "a": 656, "b": 8, "ans": 82}, {"op": "÷", "a": 664, "b": 8, "ans": 83}, {"op": "÷", "a": 672, "b": 8, "ans": 84}, {"op": "÷", "a": 680, "b": 8, "ans": 85}, {"op": "÷", "a": 688, "b": 8, "ans": 86}, {"op": "÷", "a": 696, "b": 8, "ans": 87}, {"op": "÷", "a": 704, "b": 8, "ans": 88}, {"op": "÷", "a": 712, "b": 8, "ans": 89}, {"op": "÷", "a": 720, "b": 8, "ans": 90}, {"op": "÷", "a": 728, "b": 8, "ans": 91}, {"op": "÷", "a": 736, "b": 8, "ans": 92}, {"op": "÷", "a": 744, "b": 8, "ans": 93}, {"op": "÷", "a": 752, "b": 8, "ans": 94}, {"op": "÷", "a": 760, "b": 8, "ans": 95}, {"op": "÷", "a": 768, "b": 8, "ans": 96}, {"op": "÷", "a": 776, "b": 8, "ans": 97}, {"op": "÷", "a": 784, "b": 8, "ans": 98}, {"op": "÷", "a": 792, "b": 8, "ans": 99}, {"op": "÷", "a": 800, "b": 8, "ans": 100}, {"op": "÷", "a": 808, "b": 8, "ans": 101}, {"op": "÷", "a": 816, "b": 8, "ans": 102}, {"op": "÷", "a": 824, "b": 8, "ans": 103}, {"op": "÷", "a": 832, "b": 8, "ans": 104}, {"op": "÷", "a": 840, "b": 8, "ans": 105}, {"op": "÷", "a": 848, "b": 8, "ans": 106}, {"op": "÷", "a": 856, "b": 8, "ans": 107}, {"op": "÷", "a": 864, "b": 8, "ans": 108}, {"op": "÷", "a": 872, "b": 8, "ans": 109}, {"op": "÷", "a": 880, "b": 8, "ans": 110}, {"op": "÷", "a": 888, "b": 8, "ans": 111}, {"op": "÷", "a": 896, "b": 8, "ans": 112}, {"op": "÷", "a": 904, "b": 8, "ans": 113}, {"op": "÷", "a": 912, "b": 8, "ans": 114}, {"op": "÷", "a": 920, "b": 8, "ans": 115}, {"op": "÷", "a": 928, "b": 8, "ans": 116}, {"op": "÷", "a": 936, "b": 8, "ans": 117}, {"op": "÷", "a": 944, "b": 8, "ans": 118}, {"op": "÷", "a": 952, "b": 8, "ans": 119}, {"op": "÷", "a": 960, "b": 8, "ans": 120}, {"op": "÷", "a": 968, "b": 8, "ans": 121}, {"op": "÷", "a": 976, "b": 8, "ans": 122}, {"op": "÷", "a": 984, "b": 8, "ans": 123}, {"op": "÷", "a": 992, "b": 8, "ans": 124}, {"op": "÷", "a": 108, "b": 9, "ans": 12}, {"op": "÷", "a": 117, "b": 9, "ans": 13}, {"op": "÷", "a": 126, "b": 9, "ans": 14}, {"op": "÷", "a": 135, "b": 9, "ans": 15}, {"op": "÷", "a": 144, "b": 9, "ans": 16}, {"op": "÷", "a": 153, "b": 9, "ans": 17}, {"op": "÷", "a": 162, "b": 9, "ans": 18}, {"op": "÷", "a": 171, "b": 9, "ans": 19}, {"op": "÷", "a": 180, "b": 9, "ans": 20}, {"op": "÷", "a": 189, "b": 9, "ans": 21}, {"op": "÷", "a": 198, "b": 9, "ans": 22}, {"op": "÷", "a": 207, "b": 9, "ans": 23}, {"op": "÷", "a": 216, "b": 9, "ans": 24}, {"op": "÷", "a": 225, "b": 9, "ans": 25}, {"op": "÷", "a": 234, "b": 9, "ans": 26}, {"op": "÷", "a": 243, "b": 9, "ans": 27}, {"op": "÷", "a": 252, "b": 9, "ans": 28}, {"op": "÷", "a": 261, "b": 9, "ans": 29}, {"op": "÷", "a": 270, "b": 9, "ans": 30}, {"op": "÷", "a": 279, "b": 9, "ans": 31}, {"op": "÷", "a": 288, "b": 9, "ans": 32}, {"op": "÷", "a": 297, "b": 9, "ans": 33}, {"op": "÷", "a": 306, "b": 9, "ans": 34}, {"op": "÷", "a": 315, "b": 9, "ans": 35}, {"op": "÷", "a": 324, "b": 9, "ans": 36}, {"op": "÷", "a": 333, "b": 9, "ans": 37}, {"op": "÷", "a": 342, "b": 9, "ans": 38}, {"op": "÷", "a": 351, "b": 9, "ans": 39}, {"op": "÷", "a": 360, "b": 9, "ans": 40}, {"op": "÷", "a": 369, "b": 9, "ans": 41}, {"op": "÷", "a": 378, "b": 9, "ans": 42}, {"op": "÷", "a": 387, "b": 9, "ans": 43}, {"op": "÷", "a": 396, "b": 9, "ans": 44}, {"op": "÷", "a": 405, "b": 9, "ans": 45}, {"op": "÷", "a": 414, "b": 9, "ans": 46}, {"op": "÷", "a": 423, "b": 9, "ans": 47}, {"op": "÷", "a": 432, "b": 9, "ans": 48}, {"op": "÷", "a": 441, "b": 9, "ans": 49}, {"op": "÷", "a": 450, "b": 9, "ans": 50}, {"op": "÷", "a": 459, "b": 9, "ans": 51}, {"op": "÷", "a": 468, "b": 9, "ans": 52}, {"op": "÷", "a": 477, "b": 9, "ans": 53}, {"op": "÷", "a": 486, "b": 9, "ans": 54}, {"op": "÷", "a": 495, "b": 9, "ans": 55}, {"op": "÷", "a": 504, "b": 9, "ans": 56}, {"op": "÷", "a": 513, "b": 9, "ans": 57}, {"op": "÷", "a": 522, "b": 9, "ans": 58}, {"op": "÷", "a": 531, "b": 9, "ans": 59}, {"op": "÷", "a": 540, "b": 9, "ans": 60}, {"op": "÷", "a": 549, "b": 9, "ans": 61}, {"op": "÷", "a": 558, "b": 9, "ans": 62}, {"op": "÷", "a": 567, "b": 9, "ans": 63}, {"op": "÷", "a": 576, "b": 9, "ans": 64}, {"op": "÷", "a": 585, "b": 9, "ans": 65}, {"op": "÷", "a": 594, "b": 9, "ans": 66}, {"op": "÷", "a": 603, "b": 9, "ans": 67}, {"op": "÷", "a": 612, "b": 9, "ans": 68}, {"op": "÷", "a": 621, "b": 9, "ans": 69}, {"op": "÷", "a": 630, "b": 9, "ans": 70}, {"op": "÷", "a": 639, "b": 9, "ans": 71}, {"op": "÷", "a": 648, "b": 9, "ans": 72}, {"op": "÷", "a": 657, "b": 9, "ans": 73}, {"op": "÷", "a": 666, "b": 9, "ans": 74}, {"op": "÷", "a": 675, "b": 9, "ans": 75}, {"op": "÷", "a": 684, "b": 9, "ans": 76}, {"op": "÷", "a": 693, "b": 9, "ans": 77}, {"op": "÷", "a": 702, "b": 9, "ans": 78}, {"op": "÷", "a": 711, "b": 9, "ans": 79}, {"op": "÷", "a": 720, "b": 9, "ans": 80}, {"op": "÷", "a": 729, "b": 9, "ans": 81}, {"op": "÷", "a": 738, "b": 9, "ans": 82}, {"op": "÷", "a": 747, "b": 9, "ans": 83}, {"op": "÷", "a": 756, "b": 9, "ans": 84}, {"op": "÷", "a": 765, "b": 9, "ans": 85}, {"op": "÷", "a": 774, "b": 9, "ans": 86}, {"op": "÷", "a": 783, "b": 9, "ans": 87}, {"op": "÷", "a": 792, "b": 9, "ans": 88}, {"op": "÷", "a": 801, "b": 9, "ans": 89}, {"op": "÷", "a": 810, "b": 9, "ans": 90}, {"op": "÷", "a": 819, "b": 9, "ans": 91}, {"op": "÷", "a": 828, "b": 9, "ans": 92}, {"op": "÷", "a": 837, "b": 9, "ans": 93}, {"op": "÷", "a": 846, "b": 9, "ans": 94}, {"op": "÷", "a": 855, "b": 9, "ans": 95}, {"op": "÷", "a": 864, "b": 9, "ans": 96}, {"op": "÷", "a": 873, "b": 9, "ans": 97}, {"op": "÷", "a": 882, "b": 9, "ans": 98}, {"op": "÷", "a": 891, "b": 9, "ans": 99}, {"op": "÷", "a": 900, "b": 9, "ans": 100}, {"op": "÷", "a": 909, "b": 9, "ans": 101}, {"op": "÷", "a": 918, "b": 9, "ans": 102}, {"op": "÷", "a": 927, "b": 9, "ans": 103}, {"op": "÷", "a": 936, "b": 9, "ans": 104}, {"op": "÷", "a": 945, "b": 9, "ans": 105}, {"op": "÷", "a": 954, "b": 9, "ans": 106}, {"op": "÷", "a": 963, "b": 9, "ans": 107}, {"op": "÷", "a": 972, "b": 9, "ans": 108}, {"op": "÷", "a": 981, "b": 9, "ans": 109}, {"op": "÷", "a": 990, "b": 9, "ans": 110}, {"op": "÷", "a": 999, "b": 9, "ans": 111}]